{
    "exam": {
        "id": "it_strategist",
        "title": "ITストラテジスト試験",
        "description": "ITストラテジスト試験は、経営戦略に基づきIT（情報技術）を活用して事業革新・業務改革・競争優位の創出を企画・推進できる「高度IT人材」を選抜する国家試験です。午前Ⅰ・午前Ⅱ・午後Ⅰ・午後Ⅱという４つの区分を１日で受験し、幅広い知識と実務的思考、論述力を問われます。年１回、春期に実施され、CIOやITコンサルタント、IT戦略立案などのキャリアを目指す方に適しています。",
        "price": "7,500円",
        "difficulty": "難しい",
        "official-site": "https://www.ipa.go.jp/shiken/kubun/st.html",
        "version": "CBT",
        "category": {
            "id": "it",
            "name": "情報処理技術者"
        }
    },
    "questions": [
        {
            "id": "it-ST-q1",
            "question": "DX（デジタルトランスフォーメーション）の推進における経営層の役割として最も適切なものはどれか。",
            "difficulty": "normal",
            "choices": [
                {
                    "key": "A",
                    "text": "IT部門に全てを一任し、経営戦略とは切り離して進める",
                    "explanation": {
                        "text": "DXは経営戦略と一体で推進する必要があるため、IT部門に丸投げするのは誤りです。",
                        "reference": "https://www.ipa.go.jp/digital/dx/index.html",
                        "reference_label": "IPA デジタルトランスフォーメーションの推進"
                    }
                },
                {
                    "key": "B",
                    "text": "経営戦略と整合したDXの方向性を示し、全社的な推進体制を整える",
                    "explanation": {
                        "text": "経営層はDXを経営戦略と統合し、方向性を示すリーダーシップを発揮することが重要です。",
                        "reference": "https://www.ipa.go.jp/digital/dx/index.html",
                        "reference_label": "IPA デジタルトランスフォーメーションの推進"
                    }
                },
                {
                    "key": "C",
                    "text": "最新のIT技術を全て導入し、短期間で成果を出すことに注力する",
                    "explanation": {
                        "text": "短期的成果よりも中長期的な価値創出がDXの目的であり、技術導入自体が目的ではありません。",
                        "reference": "https://www.ipa.go.jp/digital/dx/index.html",
                        "reference_label": "IPA デジタルトランスフォーメーションの推進"
                    }
                },
                {
                    "key": "D",
                    "text": "業務プロセス改善は現場に任せ、経営は関与しない",
                    "explanation": {
                        "text": "DXは業務改善にとどまらず企業変革を目指すため、経営層の積極的関与が必須です。",
                        "reference": "https://www.ipa.go.jp/digital/dx/index.html",
                        "reference_label": "IPA デジタルトランスフォーメーションの推進"
                    }
                }
            ],
            "answer": "B",
            "explanation": {
                "text": "DXは単なる技術導入ではなく、経営戦略と一体で推進する変革です。経営層は方向性を示し、全社を巻き込む推進体制を構築する責任があります。",
                "reference": "https://www.ipa.go.jp/digital/dx/index.html",
                "reference_label": "IPA デジタルトランスフォーメーションの推進"
            }
        },
        {
            "id": "it-ST-q2",
            "question": "クラウドサービス導入におけるベンダーロックインのリスクを軽減する方法として最も適切なものはどれか。",
            "difficulty": "normal",
            "choices": [
                {
                    "key": "A",
                    "text": "特定クラウドの独自サービスに依存する設計を採用する",
                    "explanation": {
                        "text": "独自サービスに依存すると移行が困難になり、ベンダーロックインが強まります。",
                        "reference": "https://www.ipa.go.jp/security/cloud/index.html",
                        "reference_label": "IPA クラウド利用セキュリティ"
                    }
                },
                {
                    "key": "B",
                    "text": "オープンスタンダードやマルチクラウド対応の設計を採用する",
                    "explanation": {
                        "text": "標準化技術や複数クラウド対応を取り入れることで移行性を高め、ロックインを軽減できます。",
                        "reference": "https://www.ipa.go.jp/security/cloud/index.html",
                        "reference_label": "IPA クラウド利用セキュリティ"
                    }
                },
                {
                    "key": "C",
                    "text": "導入後に移行コストが高くても、そのまま利用を続ける",
                    "explanation": {
                        "text": "移行困難を理由に利用を継続することはリスク軽減にはなりません。",
                        "reference": "https://www.ipa.go.jp/security/cloud/index.html",
                        "reference_label": "IPA クラウド利用セキュリティ"
                    }
                },
                {
                    "key": "D",
                    "text": "すべての業務を一つのクラウドに集約する",
                    "explanation": {
                        "text": "単一クラウドへの依存はロックインリスクを高めます。",
                        "reference": "https://www.ipa.go.jp/security/cloud/index.html",
                        "reference_label": "IPA クラウド利用セキュリティ"
                    }
                }
            ],
            "answer": "B",
            "explanation": {
                "text": "ベンダーロックインのリスク軽減には、オープン技術やマルチクラウド戦略の採用が有効です。",
                "reference": "https://www.ipa.go.jp/security/cloud/index.html",
                "reference_label": "IPA クラウド利用セキュリティ"
            }
        },
        {
            "id": "it-ST-q3",
            "question": "ゼロトラストセキュリティの基本的な考え方として正しいものはどれか。",
            "difficulty": "normal",
            "choices": [
                {
                    "key": "A",
                    "text": "社内ネットワーク内部は全て信頼できる前提とする",
                    "explanation": {
                        "text": "ゼロトラストでは内部ネットワークも信頼せず、常に検証を行います。",
                        "reference": "https://www.ipa.go.jp/security/zero-trust/index.html",
                        "reference_label": "IPA ゼロトラスト"
                    }
                },
                {
                    "key": "B",
                    "text": "ユーザーやデバイスごとに継続的に認証・認可を行う",
                    "explanation": {
                        "text": "ゼロトラストの核心は「信頼せず常に検証」であり、継続的な認証・認可が基本です。",
                        "reference": "https://www.ipa.go.jp/security/zero-trust/index.html",
                        "reference_label": "IPA ゼロトラスト"
                    }
                },
                {
                    "key": "C",
                    "text": "一度認証したら以後は無制限にアクセスを許可する",
                    "explanation": {
                        "text": "一度の認証で全アクセスを許可するのはゼロトラストの考え方に反します。",
                        "reference": "https://www.ipa.go.jp/security/zero-trust/index.html",
                        "reference_label": "IPA ゼロトラスト"
                    }
                },
                {
                    "key": "D",
                    "text": "VPN接続を使えばゼロトラストは不要となる",
                    "explanation": {
                        "text": "VPNは境界防御の一環であり、ゼロトラストを代替するものではありません。",
                        "reference": "https://www.ipa.go.jp/security/zero-trust/index.html",
                        "reference_label": "IPA ゼロトラスト"
                    }
                }
            ],
            "answer": "B",
            "explanation": {
                "text": "ゼロトラストは「すべてを信頼せず常に検証する」モデルであり、ユーザーやデバイスごとの継続的な認証・認可が基本です。",
                "reference": "https://www.ipa.go.jp/security/zero-trust/index.html",
                "reference_label": "IPA ゼロトラスト"
            }
        },
        {
            "id": "it-ST-q4",
            "question": "ITガバナンスにおいて「責任の明確化」が重要とされる理由はどれか。",
            "difficulty": "easy",
            "choices": [
                {
                    "key": "A",
                    "text": "IT部門の負担を減らすため",
                    "explanation": {
                        "text": "目的は負担軽減ではなく、役割と責任を明確化して適切に管理することです。",
                        "reference": "https://www.ipa.go.jp/security/it-governance/index.html",
                        "reference_label": "IPA ITガバナンス"
                    }
                },
                {
                    "key": "B",
                    "text": "不正アクセスを防止するため",
                    "explanation": {
                        "text": "セキュリティ強化は重要ですが、責任の明確化の本質的な目的ではありません。",
                        "reference": "https://www.ipa.go.jp/security/it-governance/index.html",
                        "reference_label": "IPA ITガバナンス"
                    }
                },
                {
                    "key": "C",
                    "text": "ITの利活用に関する意思決定と結果の責任を組織で明確にするため",
                    "explanation": {
                        "text": "ITガバナンスでは誰がどの意思決定に責任を持つかを明確にし、組織全体の整合性を保つことが重要です。",
                        "reference": "https://www.ipa.go.jp/security/it-governance/index.html",
                        "reference_label": "IPA ITガバナンス"
                    }
                },
                {
                    "key": "D",
                    "text": "システム開発を迅速化するため",
                    "explanation": {
                        "text": "迅速化は副次的な効果であり、責任の明確化の主目的ではありません。",
                        "reference": "https://www.ipa.go.jp/security/it-governance/index.html",
                        "reference_label": "IPA ITガバナンス"
                    }
                }
            ],
            "answer": "C",
            "explanation": {
                "text": "ITガバナンスでは、IT活用における意思決定権限と責任を明確にすることで、組織全体の戦略的活用を確実にします。",
                "reference": "https://www.ipa.go.jp/security/it-governance/index.html",
                "reference_label": "IPA ITガバナンス"
            }
        },
        {
            "id": "it-ST-q5",
            "question": "EA（エンタープライズ・アーキテクチャ）の導入目的として最も適切なものはどれか。",
            "difficulty": "normal",
            "choices": [
                {
                    "key": "A",
                    "text": "最新のIT技術を必ず導入するため",
                    "explanation": {
                        "text": "EAの目的は最新技術導入ではなく、全体最適の観点でITと業務を整合させることです。",
                        "reference": "https://www.ipa.go.jp/ea/index.html",
                        "reference_label": "IPA エンタープライズ・アーキテクチャ"
                    }
                },
                {
                    "key": "B",
                    "text": "業務とシステムを統合的に設計・管理し、全体最適化を図るため",
                    "explanation": {
                        "text": "EAは業務・情報・アプリケーション・技術の4領域を統合的に設計し、組織全体の整合性を高める枠組みです。",
                        "reference": "https://www.ipa.go.jp/ea/index.html",
                        "reference_label": "IPA エンタープライズ・アーキテクチャ"
                    }
                },
                {
                    "key": "C",
                    "text": "システム開発のスピードを最優先するため",
                    "explanation": {
                        "text": "開発スピードは副次的であり、EAの本質は全体最適化です。",
                        "reference": "https://www.ipa.go.jp/ea/index.html",
                        "reference_label": "IPA エンタープライズ・アーキテクチャ"
                    }
                },
                {
                    "key": "D",
                    "text": "既存システムをそのまま維持するため",
                    "explanation": {
                        "text": "EAは変革と整合を目的としており、現状維持が目的ではありません。",
                        "reference": "https://www.ipa.go.jp/ea/index.html",
                        "reference_label": "IPA エンタープライズ・アーキテクチャ"
                    }
                }
            ],
            "answer": "B",
            "explanation": {
                "text": "EAは業務・情報・システムを統合的に設計することで全体最適化を実現する枠組みです。",
                "reference": "https://www.ipa.go.jp/ea/index.html",
                "reference_label": "IPA エンタープライズ・アーキテクチャ"
            }
        },
        {
            "id": "it-ST-q6",
            "question": "システム開発におけるアジャイル開発の特徴として適切なものはどれか。",
            "difficulty": "easy",
            "choices": [
                {
                    "key": "A",
                    "text": "事前に詳細設計をすべて完了させてから開発を開始する",
                    "explanation": {
                        "text": "これはウォーターフォール開発の特徴であり、アジャイルではありません。",
                        "reference": "https://www.ipa.go.jp/ikc/reports/itss2022/itss2022.pdf",
                        "reference_label": "IPA ITスキル標準 2022"
                    }
                },
                {
                    "key": "B",
                    "text": "短いサイクルで反復し、利用者からのフィードバックを取り入れる",
                    "explanation": {
                        "text": "アジャイル開発の特徴は反復型であり、利用者との協働を重視します。",
                        "reference": "https://www.ipa.go.jp/ikc/reports/itss2022/itss2022.pdf",
                        "reference_label": "IPA ITスキル標準 2022"
                    }
                },
                {
                    "key": "C",
                    "text": "要件を初期に固定し、変更は原則受け付けない",
                    "explanation": {
                        "text": "アジャイルは変化を受け入れる開発手法です。",
                        "reference": "https://www.ipa.go.jp/ikc/reports/itss2022/itss2022.pdf",
                        "reference_label": "IPA ITスキル標準 2022"
                    }
                },
                {
                    "key": "D",
                    "text": "納品時にまとめてユーザーテストを行う",
                    "explanation": {
                        "text": "アジャイルでは開発サイクルごとにテストを行います。",
                        "reference": "https://www.ipa.go.jp/ikc/reports/itss2022/itss2022.pdf",
                        "reference_label": "IPA ITスキル標準 2022"
                    }
                }
            ],
            "answer": "B",
            "explanation": {
                "text": "アジャイル開発では短いサイクルで反復し、利用者との協働を重視します。",
                "reference": "https://www.ipa.go.jp/ikc/reports/itss2022/itss2022.pdf",
                "reference_label": "IPA ITスキル標準 2022"
            }
        },
        {
            "id": "it-ST-q7",
            "question": "データ駆動型経営（Data-Driven Management）の推進において最も重要な要素はどれか。",
            "difficulty": "normal",
            "choices": [
                {
                    "key": "A",
                    "text": "経営者の直感に基づく意思決定",
                    "explanation": {
                        "text": "直感は意思決定に役立つ場合もありますが、データ駆動型経営の本質ではありません。",
                        "reference": "https://www.ipa.go.jp/digital/data/index.html",
                        "reference_label": "IPA データ活用"
                    }
                },
                {
                    "key": "B",
                    "text": "組織内外のデータを収集・分析し、意思決定に活用する仕組み",
                    "explanation": {
                        "text": "データ駆動型経営では、信頼できるデータの収集と分析基盤を整備し、経営判断に活用することが重要です。",
                        "reference": "https://www.ipa.go.jp/digital/data/index.html",
                        "reference_label": "IPA データ活用"
                    }
                },
                {
                    "key": "C",
                    "text": "システム導入コストを最小化すること",
                    "explanation": {
                        "text": "コスト削減は副次的要素であり、データ活用の本質ではありません。",
                        "reference": "https://www.ipa.go.jp/digital/data/index.html",
                        "reference_label": "IPA データ活用"
                    }
                },
                {
                    "key": "D",
                    "text": "最新の分析ツールを導入すること自体",
                    "explanation": {
                        "text": "ツール導入自体ではなく、データに基づく意思決定プロセスが重要です。",
                        "reference": "https://www.ipa.go.jp/digital/data/index.html",
                        "reference_label": "IPA データ活用"
                    }
                }
            ],
            "answer": "B",
            "explanation": {
                "text": "データ駆動型経営の核は、信頼できるデータを収集・分析し、戦略的な意思決定に活用することです。",
                "reference": "https://www.ipa.go.jp/digital/data/index.html",
                "reference_label": "IPA データ活用"
            }
        },
    {
      "id": "it-ST-q8",
      "question": "IT投資ポートフォリオ管理において、戦略的投資と維持運用投資を区分する主な目的として最も適切なものはどれか。",
      "difficulty": "normal",
      "choices": [
        {
          "key": "A",
          "text": "最新技術の導入率を高めるため",
          "explanation": {
            "text": "導入率向上は結果であり、区分の本来目的は資源配分の最適化です。",
            "reference": "https://www.ipa.go.jp/ikc/reports/it_management/itpm.html",
            "reference_label": "IPA IT経営／IT投資マネジメント解説"
          }
        },
        {
          "key": "B",
          "text": "IT投資をリスク・リターンで分類し、資源配分を最適化するため",
          "explanation": {
            "text": "戦略的投資（成長・変革）と維持運用投資（安定・既存維持）を分けて意思決定の質を高めるのが目的です。",
            "reference": "https://www.ipa.go.jp/ikc/reports/it_management/itpm.html",
            "reference_label": "IPA IT経営／IT投資マネジメント解説"
          }
        },
        {
          "key": "C",
          "text": "監査対応を容易にするためだけ",
          "explanation": {
            "text": "監査容易化は副次的効果であり、主要目的ではありません。",
            "reference": "https://www.ipa.go.jp/ikc/reports/it_management/itpm.html",
            "reference_label": "IPA IT経営／IT投資マネジメント解説"
          }
        },
        {
          "key": "D",
          "text": "ベンダーの選択肢を減らすため",
          "explanation": {
            "text": "選択肢を狭めることは目的ではなく、むしろ客観的な評価枠組みが重要です。",
            "reference": "https://www.ipa.go.jp/ikc/reports/it_management/itpm.html",
            "reference_label": "IPA IT経営／IT投資マネジメント解説"
          }
        }
      ],
      "answer": "B",
      "explanation": {
        "text": "投資区分は、戦略（変革・成長）と維持（安定・既存）のバランスを可視化し、リスク・リターンに基づく資源配分を最適化するために行う。",
        "reference": "https://www.ipa.go.jp/ikc/reports/it_management/itpm.html",
        "reference_label": "IPA IT経営／IT投資マネジメント解説"
      }
    },
    {
      "id": "it-ST-q9",
      "question": "RFP（提案依頼書）において、機能要件と非機能要件を明確化することの主な効果として最も適切なものはどれか。",
      "difficulty": "normal",
      "choices": [
        {
          "key": "A",
          "text": "見積金額を低く抑えられることが保証される",
          "explanation": {
            "text": "金額低減は保証されず、要件明確化の直接の目的ではありません。",
            "reference": "https://www.ipa.go.jp/security/publications/guide/rfp.html",
            "reference_label": "IPA 調達における情報セキュリティ要求仕様ガイド（RFPの考え方）"
          }
        },
        {
          "key": "B",
          "text": "品質・性能・可用性などの期待水準を合意でき、後工程のリスクを低減できる",
          "explanation": {
            "text": "非機能要件（可用性、性能、保守性、セキュリティ等）を明確化することで合意形成とリスク低減が図れる。",
            "reference": "https://www.ipa.go.jp/security/publications/guide/rfp.html",
            "reference_label": "IPA 調達における情報セキュリティ要求仕様ガイド（RFPの考え方）"
          }
        },
        {
          "key": "C",
          "text": "ベンダーの技術選定に発注者が介入できなくなる",
          "explanation": {
            "text": "要件定義は成果の期待値を定めるもので、介入不可を意味しません。",
            "reference": "https://www.ipa.go.jp/security/publications/guide/rfp.html",
            "reference_label": "IPA 調達における情報セキュリティ要求仕様ガイド（RFPの考え方）"
          }
        },
        {
          "key": "D",
          "text": "契約形態が自動的に成果物契約（完了検収型）に限定される",
          "explanation": {
            "text": "契約形態は案件特性で判断され、要件明確化により限定されるものではありません。",
            "reference": "https://www.ipa.go.jp/security/publications/guide/rfp.html",
            "reference_label": "IPA 調達における情報セキュリティ要求仕様ガイド（RFPの考え方）"
          }
        }
      ],
      "answer": "B",
      "explanation": {
        "text": "機能・非機能要件を明確にすることで、品質・性能・セキュリティなどの期待値を事前合意でき、スコープブレや品質不一致のリスクを下げられる。",
        "reference": "https://www.ipa.go.jp/security/publications/guide/rfp.html",
        "reference_label": "IPA 調達における情報セキュリティ要求仕様ガイド（RFPの考え方）"
      }
    },
    {
      "id": "it-ST-q10",
      "question": "サイバーセキュリティ経営ガイドラインにおいて、経営者が担うべき役割として適切なものはどれか。",
      "difficulty": "normal",
      "choices": [
        {
          "key": "A",
          "text": "CSIRTの詳細な技術手順書を経営者自身が作成する",
          "explanation": {
            "text": "技術手順作成は実務責任者の役割であり、経営者は方針と資源配分を担います。",
            "reference": "https://www.meti.go.jp/policy/netsecurity/mng_guide.html",
            "reference_label": "経産省・IPA サイバーセキュリティ経営ガイドライン"
          }
        },
        {
          "key": "B",
          "text": "重要情報資産とリスクの特定、対策の優先順位付け、体制・資源の確保を主導する",
          "explanation": {
            "text": "経営者はリスクベースでの意思決定と体制整備を主導すべきとされます。",
            "reference": "https://www.meti.go.jp/policy/netsecurity/mng_guide.html",
            "reference_label": "経産省・IPA サイバーセキュリティ経営ガイドライン"
          }
        },
        {
          "key": "C",
          "text": "セキュリティはIT部門の自己責任とし、経営は関与しない",
          "explanation": {
            "text": "ガイドラインは経営課題としての関与を強く求めています。",
            "reference": "https://www.meti.go.jp/policy/netsecurity/mng_guide.html",
            "reference_label": "経産省・IPA サイバーセキュリティ経営ガイドライン"
          }
        },
        {
          "key": "D",
          "text": "法令遵守は監査部門のみの責務であると位置付ける",
          "explanation": {
            "text": "法令遵守は経営の責任の下で全社的に取り組むものです。",
            "reference": "https://www.meti.go.jp/policy/netsecurity/mng_guide.html",
            "reference_label": "経産省・IPA サイバーセキュリティ経営ガイドライン"
          }
        }
      ],
      "answer": "B",
      "explanation": {
        "text": "ガイドラインは経営者の責務として、重要資産とリスクの把握、対策優先度の決定、体制・予算の確保と継続的改善を明示している。",
        "reference": "https://www.meti.go.jp/policy/netsecurity/mng_guide.html",
        "reference_label": "経産省・IPA サイバーセキュリティ経営ガイドライン"
      }
    },
    {
      "id": "it-ST-q11",
      "question": "クラウドの責任共有モデルにおいて、IaaS利用時に利用者（顧客）が主に責任を負う領域として最も適切なものはどれか。",
      "difficulty": "easy",
      "choices": [
        {
          "key": "A",
          "text": "ハイパーバイザーと物理データセンタの運用",
          "explanation": {
            "text": "基盤の運用はクラウド事業者の責任範囲です。",
            "reference": "https://www.ipa.go.jp/security/cloud/guide.html",
            "reference_label": "IPA クラウドセキュリティガイド（責任共有の考え方）"
          }
        },
        {
          "key": "B",
          "text": "OS設定、ミドルウェア、アプリ、データ、アイデンティティ管理などのセキュリティ設定",
          "explanation": {
            "text": "IaaSではゲストOS以上のレイヤは利用者の責任が中心となります。",
            "reference": "https://www.ipa.go.jp/security/cloud/guide.html",
            "reference_label": "IPA クラウドセキュリティガイド（責任共有の考え方）"
          }
        },
        {
          "key": "C",
          "text": "ネットワーク機器の物理交換作業",
          "explanation": {
            "text": "物理ハードの保守はクラウド事業者側の責任です。",
            "reference": "https://www.ipa.go.jp/security/cloud/guide.html",
            "reference_label": "IPA クラウドセキュリティガイド（責任共有の考え方）"
          }
        },
        {
          "key": "D",
          "text": "電源設備と建屋の耐震対策",
          "explanation": {
            "text": "施設レベルの対策はクラウド事業者の責任です。",
            "reference": "https://www.ipa.go.jp/security/cloud/guide.html",
            "reference_label": "IPA クラウドセキュリティガイド（責任共有の考え方）"
          }
        }
      ],
      "answer": "B",
      "explanation": {
        "text": "責任共有では、IaaS利用時は基盤下層は事業者、OS以上（設定・アクセス管理・データ保護等）は利用者が主に担う。",
        "reference": "https://www.ipa.go.jp/security/cloud/guide.html",
        "reference_label": "IPA クラウドセキュリティガイド（責任共有の考え方）"
      }
    },
    {
      "id": "it-ST-q12",
      "question": "リスクアセスメントにおける“リスク受容”の判断が妥当となる条件として最も適切なものはどれか。",
      "difficulty": "normal",
      "choices": [
        {
          "key": "A",
          "text": "リスク対応の予算が不足しているため受容する",
          "explanation": {
            "text": "予算不足のみを理由とする受容は不適切です。許容基準に基づく判断が必要です。",
            "reference": "https://www.ipa.go.jp/security/isec/jisq27001.html",
            "reference_label": "IPA ISMS関連解説（JIS Q 27001/27005の考え方）"
          }
        },
        {
          "key": "B",
          "text": "リスクが許容基準以下であり、残存リスクも事業目標に照らして受容可能である",
          "explanation": {
            "text": "リスク受容は定義されたリスク許容基準に合致し、経営の承認を得た場合に妥当です。",
            "reference": "https://www.ipa.go.jp/security/isec/jisq27001.html",
            "reference_label": "IPA ISMS関連解説（JIS Q 27001/27005の考え方）"
          }
        },
        {
          "key": "C",
          "text": "発生頻度が低ければ影響が極大でも常に受容できる",
          "explanation": {
            "text": "影響が極大で事業継続に支障がある場合、頻度が低くても受容は妥当ではありません。",
            "reference": "https://www.ipa.go.jp/security/isec/jisq27001.html",
            "reference_label": "IPA ISMS関連解説（JIS Q 27001/27005の考え方）"
          }
        },
        {
          "key": "D",
          "text": "外部委託先が対応する予定なので受容する",
          "explanation": {
            "text": "委託先任せは責任移転の検討事項であり、受容の根拠にはなりません。",
            "reference": "https://www.ipa.go.jp/security/isec/jisq27001.html",
            "reference_label": "IPA ISMS関連解説（JIS Q 27001/27005の考え方）"
          }
        }
      ],
      "answer": "B",
      "explanation": {
        "text": "受容は“許容基準以下であること”“経営承認”“残存リスクの妥当性”が条件で、予算不足などの便宜的理由では正当化できない。",
        "reference": "https://www.ipa.go.jp/security/isec/jisq27001.html",
        "reference_label": "IPA ISMS関連解説（JIS Q 27001/27005の考え方）"
      }
    },
    {
      "id": "it-ST-q13",
      "question": "個人情報保護法における「仮名加工情報」と「匿名加工情報」の相違として正しいものはどれか。",
      "difficulty": "hard",
      "choices": [
        {
          "key": "A",
          "text": "両者とも第三者提供時に公表義務は一切ない",
          "explanation": {
            "text": "匿名加工情報は第三者提供時の公表等の義務がある一方、仮名加工情報は原則として事業者内部利用が想定されます。",
            "reference": "https://www.ppc.go.jp/personalinfo/legal/",
            "reference_label": "個人情報保護委員会 法令・ガイドライン"
          }
        },
        {
          "key": "B",
          "text": "仮名加工情報は本人の識別性を低減した情報で、事業者内部利用が想定される。匿名加工情報は復元できないよう加工され、第三者提供が可能。",
          "explanation": {
            "text": "定義と利用想定の違いを示しており、最新ガイドラインと整合します。",
            "reference": "https://www.ppc.go.jp/personalinfo/legal/",
            "reference_label": "個人情報保護委員会 法令・ガイドライン"
          }
        },
        {
          "key": "C",
          "text": "匿名加工情報は容易に元に戻せる",
          "explanation": {
            "text": "匿名加工情報は復元できないよう加工されなければなりません。",
            "reference": "https://www.ppc.go.jp/personalinfo/legal/",
            "reference_label": "個人情報保護委員会 法令・ガイドライン"
          }
        },
        {
          "key": "D",
          "text": "仮名加工情報は第三者提供が義務付けられている",
          "explanation": {
            "text": "義務付けはありません。内部利用を想定した制度です。",
            "reference": "https://www.ppc.go.jp/personalinfo/legal/",
            "reference_label": "個人情報保護委員会 法令・ガイドライン"
          }
        }
      ],
      "answer": "B",
      "explanation": {
        "text": "仮名加工情報は内部利用前提の再識別リスク低減データ、匿名加工情報は非復元性を要件とし第三者提供が可能で公表等の義務が課されるなど制度設計が異なる。",
        "reference": "https://www.ppc.go.jp/personalinfo/legal/",
        "reference_label": "個人情報保護委員会 法令・ガイドライン"
      }
    },
    {
      "id": "it-ST-q14",
      "question": "フィージビリティスタディ（実行可能性調査）で“技術的実現性”の評価項目として最も適切なものはどれか。",
      "difficulty": "easy",
      "choices": [
        {
          "key": "A",
          "text": "期待収益と投資回収期間",
          "explanation": {
            "text": "これは主に経済性の評価項目です。",
            "reference": "https://www.ipa.go.jp/ikc/reports/systematization/reqeng.html",
            "reference_label": "IPA 要求工学・システム化計画ガイド"
          }
        },
        {
          "key": "B",
          "text": "既存アーキテクチャへの適合性と必要な技術スキルの確保可能性",
          "explanation": {
            "text": "技術的適合性、保守性、スキル入手可能性は技術的実現性の主要観点です。",
            "reference": "https://www.ipa.go.jp/ikc/reports/systematization/reqeng.html",
            "reference_label": "IPA 要求工学・システム化計画ガイド"
          }
        },
        {
          "key": "C",
          "text": "法令・規制との整合性",
          "explanation": {
            "text": "重要だが主に制度的実現性（制度面）の観点に該当します。",
            "reference": "https://www.ipa.go.jp/ikc/reports/systematization/reqeng.html",
            "reference_label": "IPA 要求工学・システム化計画ガイド"
          }
        },
        {
          "key": "D",
          "text": "関係者の利害調整の見込み",
          "explanation": {
            "text": "主に組織・運用面の実現性に関する観点です。",
            "reference": "https://www.ipa.go.jp/ikc/reports/systematization/reqeng.html",
            "reference_label": "IPA 要求工学・システム化計画ガイド"
          }
        }
      ],
      "answer": "B",
      "explanation": {
        "text": "技術的実現性はアーキテクチャ適合、性能・可用性の達成可能性、必要スキル・ツールの入手容易性などで評価する。",
        "reference": "https://www.ipa.go.jp/ikc/reports/systematization/reqeng.html",
        "reference_label": "IPA 要求工学・システム化計画ガイド"
      }
    },
    {
      "id": "it-ST-q15",
      "question": "データガバナンスにおいてデータスチュワードの主な役割はどれか。",
      "difficulty": "normal",
      "choices": [
        {
          "key": "A",
          "text": "データの物理的バックアップを取得すること",
          "explanation": {
            "text": "バックアップは運用管理者の責務であり、スチュワードの役割ではありません。",
            "reference": "https://www.ipa.go.jp/digital/data/governance.html",
            "reference_label": "IPA データガバナンス"
          }
        },
        {
          "key": "B",
          "text": "データ品質の維持や利用ルールの策定・遵守を監督すること",
          "explanation": {
            "text": "データスチュワードはデータの品質・定義・利用ルールを管理し、全社的なガバナンスを担います。",
            "reference": "https://www.ipa.go.jp/digital/data/governance.html",
            "reference_label": "IPA データガバナンス"
          }
        },
        {
          "key": "C",
          "text": "データベースチューニングを行うこと",
          "explanation": {
            "text": "パフォーマンス調整はDB管理者の役割です。",
            "reference": "https://www.ipa.go.jp/digital/data/governance.html",
            "reference_label": "IPA データガバナンス"
          }
        },
        {
          "key": "D",
          "text": "データセンタの電力効率を改善すること",
          "explanation": {
            "text": "これはインフラ運用の役割です。",
            "reference": "https://www.ipa.go.jp/digital/data/governance.html",
            "reference_label": "IPA データガバナンス"
          }
        }
      ],
      "answer": "B",
      "explanation": {
        "text": "データスチュワードはデータの品質や利用ルールを統制し、組織全体のデータガバナンスを担う役割です。",
        "reference": "https://www.ipa.go.jp/digital/data/governance.html",
        "reference_label": "IPA データガバナンス"
      }
    },
    {
      "id": "it-ST-q16",
      "question": "BPR（Business Process Re-engineering）の特徴として最も適切なものはどれか。",
      "difficulty": "easy",
      "choices": [
        {
          "key": "A",
          "text": "既存業務を小規模に改善し続けることを目的とする",
          "explanation": {
            "text": "これはカイゼンの特徴であり、BPRの特徴ではありません。",
            "reference": "https://www.ipa.go.jp/ikc/reports/process/bpr.html",
            "reference_label": "IPA 業務プロセス改革解説"
          }
        },
        {
          "key": "B",
          "text": "既存の業務プロセスを抜本的に見直し、革新的な再設計を行う",
          "explanation": {
            "text": "BPRは既存業務の前提を破壊的に見直し、業務・組織を抜本改革することを特徴とします。",
            "reference": "https://www.ipa.go.jp/ikc/reports/process/bpr.html",
            "reference_label": "IPA 業務プロセス改革解説"
          }
        },
        {
          "key": "C",
          "text": "システム更新を最小化することを目的とする",
          "explanation": {
            "text": "BPRは業務全体の変革が目的であり、システム更新を抑えること自体は目的ではありません。",
            "reference": "https://www.ipa.go.jp/ikc/reports/process/bpr.html",
            "reference_label": "IPA 業務プロセス改革解説"
          }
        },
        {
          "key": "D",
          "text": "業務改善の効果を測定しない",
          "explanation": {
            "text": "BPRでは効果測定を含めた改革が必須です。",
            "reference": "https://www.ipa.go.jp/ikc/reports/process/bpr.html",
            "reference_label": "IPA 業務プロセス改革解説"
          }
        }
      ],
      "answer": "B",
      "explanation": {
        "text": "BPRは業務の前提を根本から再構築する革新的改革アプローチです。",
        "reference": "https://www.ipa.go.jp/ikc/reports/process/bpr.html",
        "reference_label": "IPA 業務プロセス改革解説"
      }
    },
    {
      "id": "it-ST-q17",
      "question": "EA（エンタープライズ・アーキテクチャ）の更新管理で重視されるべき観点はどれか。",
      "difficulty": "normal",
      "choices": [
        {
          "key": "A",
          "text": "業務やシステムの変化を反映し、現行との乖離を常に把握できる状態を維持する",
          "explanation": {
            "text": "EAは更新されて初めて経営とITの整合を維持できます。乖離把握と改善が重要です。",
            "reference": "https://www.ipa.go.jp/ea/index.html",
            "reference_label": "IPA エンタープライズ・アーキテクチャ"
          }
        },
        {
          "key": "B",
          "text": "一度作成したEAは固定し、更新は行わない",
          "explanation": {
            "text": "更新しないEAは現実と乖離し形骸化します。",
            "reference": "https://www.ipa.go.jp/ea/index.html",
            "reference_label": "IPA エンタープライズ・アーキテクチャ"
          }
        },
        {
          "key": "C",
          "text": "更新作業はIT部門だけで実施し、業務部門は関与しない",
          "explanation": {
            "text": "EAは業務とITを統合的に扱うため、業務部門の関与が不可欠です。",
            "reference": "https://www.ipa.go.jp/ea/index.html",
            "reference_label": "IPA エンタープライズ・アーキテクチャ"
          }
        },
        {
          "key": "D",
          "text": "更新は技術的要素に限定し、業務は考慮しない",
          "explanation": {
            "text": "EAは業務・情報・アプリ・技術の統合が本質であり、業務を除外しては意味がありません。",
            "reference": "https://www.ipa.go.jp/ea/index.html",
            "reference_label": "IPA エンタープライズ・アーキテクチャ"
          }
        }
      ],
      "answer": "A",
      "explanation": {
        "text": "EAは動的な経営・IT環境の変化を反映して更新し続けることで効果を発揮します。",
        "reference": "https://www.ipa.go.jp/ea/index.html",
        "reference_label": "IPA エンタープライズ・アーキテクチャ"
      }
    },
    {
      "id": "it-ST-q18",
      "question": "クラウド利用におけるコスト最適化策として最も適切なものはどれか。",
      "difficulty": "easy",
      "choices": [
        {
          "key": "A",
          "text": "常に最大リソースを確保し、利用量に関係なく稼働させる",
          "explanation": {
            "text": "これは過剰プロビジョニングでありコスト最適化に反します。",
            "reference": "https://www.ipa.go.jp/security/cloud/guide.html",
            "reference_label": "IPA クラウド利用ガイド"
          }
        },
        {
          "key": "B",
          "text": "オートスケーリングやリソースの適正サイズ化を実施する",
          "explanation": {
            "text": "需要に応じたリソース調整はクラウドのメリットを活かすコスト最適化策です。",
            "reference": "https://www.ipa.go.jp/security/cloud/guide.html",
            "reference_label": "IPA クラウド利用ガイド"
          }
        },
        {
          "key": "C",
          "text": "利用実績のモニタリングは行わない",
          "explanation": {
            "text": "モニタリングしなければ最適化はできません。",
            "reference": "https://www.ipa.go.jp/security/cloud/guide.html",
            "reference_label": "IPA クラウド利用ガイド"
          }
        },
        {
          "key": "D",
          "text": "開発・検証環境を常時稼働させる",
          "explanation": {
            "text": "不要時は停止することでコスト削減できます。",
            "reference": "https://www.ipa.go.jp/security/cloud/guide.html",
            "reference_label": "IPA クラウド利用ガイド"
          }
        }
      ],
      "answer": "B",
      "explanation": {
        "text": "クラウドの強みは需要に応じたリソース調整であり、オートスケーリングや適正化はコスト最適化に直結します。",
        "reference": "https://www.ipa.go.jp/security/cloud/guide.html",
        "reference_label": "IPA クラウド利用ガイド"
      }
    },
    {
      "id": "it-ST-q19",
      "question": "BCP（事業継続計画）におけるRTO（目標復旧時間）の意味として正しいものはどれか。",
      "difficulty": "easy",
      "choices": [
        {
          "key": "A",
          "text": "システム障害が発生しても許容される最大のデータ損失時間",
          "explanation": {
            "text": "これはRPO（目標復旧時点）の定義です。",
            "reference": "https://www.ipa.go.jp/security/bcm/index.html",
            "reference_label": "IPA 事業継続とIT"
          }
        },
        {
          "key": "B",
          "text": "事業やシステムを復旧させるまでに許容される最大時間",
          "explanation": {
            "text": "RTOはシステムや業務を再稼働させるまでの許容時間を示します。",
            "reference": "https://www.ipa.go.jp/security/bcm/index.html",
            "reference_label": "IPA 事業継続とIT"
          }
        },
        {
          "key": "C",
          "text": "バックアップの世代保持期間",
          "explanation": {
            "text": "これはバックアップ運用の設定であり、RTOではありません。",
            "reference": "https://www.ipa.go.jp/security/bcm/index.html",
            "reference_label": "IPA 事業継続とIT"
          }
        },
        {
          "key": "D",
          "text": "障害が発生する確率",
          "explanation": {
            "text": "RTOは時間に関する指標であり確率ではありません。",
            "reference": "https://www.ipa.go.jp/security/bcm/index.html",
            "reference_label": "IPA 事業継続とIT"
          }
        }
      ],
      "answer": "B",
      "explanation": {
        "text": "RTOは事業継続計画におけるシステムや業務の再稼働までの許容時間を表します。",
        "reference": "https://www.ipa.go.jp/security/bcm/index.html",
        "reference_label": "IPA 事業継続とIT"
      }
    },
    {
      "id": "it-ST-q20",
      "question": "ゼロトラストアーキテクチャの運用において「継続的モニタリング」が必要とされる主な理由はどれか。",
      "difficulty": "normal",
      "choices": [
        {
          "key": "A",
          "text": "一度認証したユーザは常に信頼できるから",
          "explanation": {
            "text": "ゼロトラストでは一度の認証で恒久的信頼はしません。",
            "reference": "https://www.ipa.go.jp/security/zero-trust/index.html",
            "reference_label": "IPA ゼロトラスト"
          }
        },
        {
          "key": "B",
          "text": "状況やリスクの変化に応じてアクセス制御を動的に適用するため",
          "explanation": {
            "text": "ゼロトラストではリアルタイムでリスク評価し、アクセス制御を調整するため継続的モニタリングが必要です。",
            "reference": "https://www.ipa.go.jp/security/zero-trust/index.html",
            "reference_label": "IPA ゼロトラスト"
          }
        },
        {
          "key": "C",
          "text": "VPN利用時にのみ必要だから",
          "explanation": {
            "text": "ゼロトラストはVPN利用有無にかかわらず適用されます。",
            "reference": "https://www.ipa.go.jp/security/zero-trust/index.html",
            "reference_label": "IPA ゼロトラスト"
          }
        },
        {
          "key": "D",
          "text": "監査コストを削減するためだけ",
          "explanation": {
            "text": "監査支援は副次的効果であり、本質は動的制御です。",
            "reference": "https://www.ipa.go.jp/security/zero-trust/index.html",
            "reference_label": "IPA ゼロトラスト"
          }
        }
      ],
      "answer": "B",
      "explanation": {
        "text": "ゼロトラストは「常に検証」が原則であり、動的にアクセスを制御するため継続的モニタリングが不可欠です。",
        "reference": "https://www.ipa.go.jp/security/zero-trust/index.html",
        "reference_label": "IPA ゼロトラスト"
      }
    },
    {
      "id": "it-ST-q21",
      "question": "生成AIの企業利用において、ガバナンス上最も重要な留意点はどれか。",
      "difficulty": "hard",
      "choices": [
        {
          "key": "A",
          "text": "生成AIの出力を常に正しいとみなし、検証せずに業務へ適用すること",
          "explanation": {
            "text": "AI出力には誤情報やバイアスが含まれる可能性があり、検証なしの利用はリスクを高める。",
            "reference": "https://www.ipa.go.jp/ikc/reports/ai/ai-governance.html",
            "reference_label": "IPA AIガバナンス"
          }
        },
        {
          "key": "B",
          "text": "利用ルールを整備し、出力の正確性検証や著作権・個人情報リスクへの対応を組み込むこと",
          "explanation": {
            "text": "AIガバナンスの核心は透明性・説明責任・リスク管理であり、ルール整備と出力検証が不可欠。",
            "reference": "https://www.ipa.go.jp/ikc/reports/ai/ai-governance.html",
            "reference_label": "IPA AIガバナンス"
          }
        },
        {
          "key": "C",
          "text": "各部門が独自に運用し、全社的な統一基準を設けないこと",
          "explanation": {
            "text": "ガバナンスは全社統一基準で運用される必要がある。部門ごとの独自運用はリスクを拡大する。",
            "reference": "https://www.ipa.go.jp/ikc/reports/ai/ai-governance.html",
            "reference_label": "IPA AIガバナンス"
          }
        },
        {
          "key": "D",
          "text": "生成AIの利用は法令遵守の対象外であるため、特別な管理は不要とすること",
          "explanation": {
            "text": "著作権や個人情報保護などの法令は適用され、ガバナンスに組み込む必要がある。",
            "reference": "https://www.ipa.go.jp/ikc/reports/ai/ai-governance.html",
            "reference_label": "IPA AIガバナンス"
          }
        }
      ],
      "answer": "B",
      "explanation": {
        "text": "生成AI利用では誤情報・権利侵害・個人情報漏洩のリスクがある。全社的なルール整備と出力検証プロセスを設けることがガバナンス上最も重要である。",
        "reference": "https://www.ipa.go.jp/ikc/reports/ai/ai-governance.html",
        "reference_label": "IPA AIガバナンス"
      }
    },
    {
      "id": "it-ST-q22",
      "question": "DX推進を経営戦略と整合させるために、ストラテジストが最初に行うべきこととして最も適切なものはどれか。",
      "difficulty": "normal",
      "choices": [
        {
          "key": "A",
          "text": "部門ごとに独自のKPIを設定し、全社統一の指標は設けない",
          "explanation": {
            "text": "部門最適のみでは全社のDX成熟度を把握できず、統一的な自己診断や指標が必要となる。",
            "reference": "https://www.ipa.go.jp/digital/dx-suishin/index.html",
            "reference_label": "IPA DX推進指標（自己診断）"
          }
        },
        {
          "key": "B",
          "text": "DX推進指標を用いて現状と課題を可視化し、経営課題とKPIを擦り合わせる",
          "explanation": {
            "text": "DX推進指標は現状把握と経営との合意形成を促す仕組みで、優先課題の整理に有効である。",
            "reference": "https://www.ipa.go.jp/digital/dx-suishin/index.html",
            "reference_label": "IPA DX推進指標（自己診断）"
          }
        },
        {
          "key": "C",
          "text": "最新技術の導入可否のみを検討し、業務・組織は後回しにする",
          "explanation": {
            "text": "DXは技術導入が目的ではなく、経営・業務と一体で変革を進める必要がある。",
            "reference": "https://www.ipa.go.jp/digital/dx/index.html",
            "reference_label": "IPA DXポータル"
          }
        },
        {
          "key": "D",
          "text": "IT部門に全てを委任し、経営層の関与は最小化する",
          "explanation": {
            "text": "DXは経営課題であり、経営主導での方向性提示と全社体制が求められる。",
            "reference": "https://www.ipa.go.jp/digital/dx/index.html",
            "reference_label": "IPA DXポータル"
          }
        }
      ],
      "answer": "B",
      "explanation": {
        "text": "DX推進では、まず現状を共通言語で可視化し、経営戦略と整合したKPIを設定することが要諦。IPAのDX推進指標はそのための実務的枠組みを提供する。",
        "reference": "https://www.ipa.go.jp/digital/dx-suishin/index.html",
        "reference_label": "IPA DX推進指標（自己診断）"
      }
    },
    {
      "id": "it-ST-q23",
      "question": "クラウド利用におけるコスト最適化の基本方針として適切なものはどれか。",
      "difficulty": "easy",
      "choices": [
        {
          "key": "A",
          "text": "常時最大リソースを確保し、ピークに合わせて固定運用する",
          "explanation": {
            "text": "過剰プロビジョニングはコスト増の主因であり、クラウドの弾力性を活かせていない。",
            "reference": "https://www.ipa.go.jp/security/sme/f55m8k0000001wpl-att/outline_guidance_cloud.pdf",
            "reference_label": "IPA 中小企業のためのクラウド安全利用の手引き"
          }
        },
        {
          "key": "B",
          "text": "利用状況を可視化し、リソースの適正サイズ化やオートスケーリングを適用する",
          "explanation": {
            "text": "需要に応じたスケーリングや停止運用はクラウドのコスト最適化の基本策である。",
            "reference": "https://www.ipa.go.jp/security/sme/f55m8k0000001wpl-att/outline_guidance_cloud.pdf",
            "reference_label": "IPA 中小企業のためのクラウド安全利用の手引き"
          }
        },
        {
          "key": "C",
          "text": "開発検証環境は削除を防ぐため常時稼働させる",
          "explanation": {
            "text": "必要時のみ起動する設計と自動停止でコストを抑制できる。",
            "reference": "https://www.ipa.go.jp/security/sme/f55m8k0000001wpl-att/outline_guidance_cloud.pdf",
            "reference_label": "IPA 中小企業のためのクラウド安全利用の手引き"
          }
        },
        {
          "key": "D",
          "text": "利用実績のレビューは四半期に1回で十分で、日次の監視は不要",
          "explanation": {
            "text": "費用の急増や設定不備は早期検知が有効で、継続的な可視化が重要である。",
            "reference": "https://www.ipa.go.jp/security/sme/f55m8k0000001wpl-att/outline_guidance_cloud.pdf",
            "reference_label": "IPA 中小企業のためのクラウド安全利用の手引き"
          }
        }
      ],
      "answer": "B",
      "explanation": {
        "text": "クラウドの強みは弾力性と従量課金。可視化・適正化・自動化を組み合わせて需要追随型のリソース運用に転換するのが定石である。",
        "reference": "https://www.ipa.go.jp/security/sme/f55m8k0000001wpl-att/outline_guidance_cloud.pdf",
        "reference_label": "IPA 中小企業のためのクラウド安全利用の手引き"
      }
    },
    {
      "id": "it-ST-q24",
      "question": "個人情報保護法における「仮名加工情報」の特徴として正しいものはどれか。",
      "difficulty": "hard",
      "choices": [
        {
          "key": "A",
          "text": "復元可能性を完全に排除しており、第三者提供時の公表義務がある",
          "explanation": {
            "text": "これは匿名加工情報の要件・義務であり、仮名加工情報の説明としては不適切。",
            "reference": "https://www.ppc.go.jp/personalinfo/legal/guidelines_anonymous/",
            "reference_label": "個人情報保護委員会 ガイドライン（仮名・匿名加工情報）"
          }
        },
        {
          "key": "B",
          "text": "他の情報と照合しない限り個人を識別できないよう加工し、主に事業者内部での利用を想定する",
          "explanation": {
            "text": "法の定義・運用想定に合致する。内部利用により利活用と保護の両立を図る制度である。",
            "reference": "https://www.ppc.go.jp/personalinfo/legal/guidelines_anonymous/",
            "reference_label": "個人情報保護委員会 ガイドライン（仮名・匿名加工情報）"
          }
        },
        {
          "key": "C",
          "text": "本人同意なく第三者提供を義務付ける制度である",
          "explanation": {
            "text": "第三者提供が義務付けられる制度ではない。",
            "reference": "https://www.ppc.go.jp/personalinfo/legal/guidelines_anonymous/",
            "reference_label": "個人情報保護委員会 ガイドライン（仮名・匿名加工情報）"
          }
        },
        {
          "key": "D",
          "text": "IPアドレス等の個人識別符号を必ず残す必要がある",
          "explanation": {
            "text": "個人識別符号の削除等、識別性を低減する措置を講ずるのが仮名加工情報の趣旨である。",
            "reference": "https://www.ppc.go.jp/personalinfo/legal/guidelines_anonymous/",
            "reference_label": "個人情報保護委員会 ガイドライン（仮名・匿名加工情報）"
          }
        }
      ],
      "answer": "B",
      "explanation": {
        "text": "仮名加工情報は“照合しない限り識別できない”状態に加工した内部活用向けの枠組みで、匿名加工情報（非復元性・第三者提供可）とは要件と運用が異なる。",
        "reference": "https://www.ppc.go.jp/personalinfo/legal/guidelines_anonymous/",
        "reference_label": "個人情報保護委員会 ガイドライン（仮名・匿名加工情報）"
      }
    },
    {
      "id": "it-ST-q25",
      "question": "ゼロトラストの運用で、アクセスごとにポリシー判断を行うために重要な設計要素はどれか。",
      "difficulty": "normal",
      "choices": [
        {
          "key": "A",
          "text": "初回認証後はネットワーク内全資源へのアクセスを許可する境界型モデル",
          "explanation": {
            "text": "境界型は“内は信頼”が前提でゼロトラストと相反する。",
            "reference": "https://www.ipa.go.jp/security/zero-trust/index.html",
            "reference_label": "IPA ゼロトラスト"
          }
        },
        {
          "key": "B",
          "text": "ユーザ属性・端末状態・位置・行動などのコンテキストを継続的に収集し評価する機構",
          "explanation": {
            "text": "“常に検証”を実現するには多面的コンテキストの継続評価が必要。",
            "reference": "https://www.ipa.go.jp/security/zero-trust/index.html",
            "reference_label": "IPA ゼロトラスト"
          }
        },
        {
          "key": "C",
          "text": "VPN接続があれば他の検証は不要とする設計",
          "explanation": {
            "text": "VPNの有無に関わらず継続的検証が求められる。",
            "reference": "https://www.ipa.go.jp/security/zero-trust/index.html",
            "reference_label": "IPA ゼロトラスト"
          }
        },
        {
          "key": "D",
          "text": "アクセス記録は保存しないが、認証だけは強固にする",
          "explanation": {
            "text": "監査と動的制御のため、ログ保全と可視化は不可欠である。",
            "reference": "https://www.ipa.go.jp/security/zero-trust/index.html",
            "reference_label": "IPA ゼロトラスト"
          }
        }
      ],
      "answer": "B",
      "explanation": {
        "text": "ゼロトラストは“常に検証”。ユーザ・端末・ネットワーク・挙動などのコンテキストを統合評価し、都度ポリシーを適用する設計が中核である。",
        "reference": "https://www.ipa.go.jp/security/zero-trust/index.html",
        "reference_label": "IPA ゼロトラスト"
      }
    },
    {
      "id": "it-ST-q26",
      "question": "RPO（目標復旧時点）の定義として適切なものはどれか。",
      "difficulty": "easy",
      "choices": [
        {
          "key": "A",
          "text": "業務・システムが再稼働するまでの許容時間",
          "explanation": {
            "text": "これはRTO（目標復旧時間）の定義である。",
            "reference": "https://www.ipa.go.jp/security/bcm/index.html",
            "reference_label": "IPA 事業継続とIT"
          }
        },
        {
          "key": "B",
          "text": "障害発生時に許容できる最大のデータ損失期間（時点）",
          "explanation": {
            "text": "RPOはどの時点までのデータが復旧できれば許容かを示す指標である。",
            "reference": "https://www.ipa.go.jp/security/bcm/index.html",
            "reference_label": "IPA 事業継続とIT"
          }
        },
        {
          "key": "C",
          "text": "バックアップ媒体の保管年限",
          "explanation": {
            "text": "媒体保管期間は運用上の設定であり、RPOの定義ではない。",
            "reference": "https://www.ipa.go.jp/security/bcm/index.html",
            "reference_label": "IPA 事業継続とIT"
          }
        },
        {
          "key": "D",
          "text": "障害の年発生確率",
          "explanation": {
            "text": "RPOは確率ではなくデータの復旧時点に関する指標である。",
            "reference": "https://www.ipa.go.jp/security/bcm/index.html",
            "reference_label": "IPA 事業継続とIT"
          }
        }
      ],
      "answer": "B",
      "explanation": {
        "text": "RPOは“どの時点までのデータが戻れば事業が耐えられるか”を定める。RTO（復旧に要する許容時間）と対でBCP/DRの設計に用いる。",
        "reference": "https://www.ipa.go.jp/security/bcm/index.html",
        "reference_label": "IPA 事業継続とIT"
      }
    },
    {
      "id": "it-ST-q27",
      "question": "クラウドサービスの調達において、RFPに非機能要件を明記する主な効果はどれか。",
      "difficulty": "normal",
      "choices": [
        {
          "key": "A",
          "text": "見積金額が必ず安くなる",
          "explanation": {
            "text": "コスト低減は保証されない。目的は期待品質の合意とリスク低減である。",
            "reference": "https://www.meti.go.jp/policy/netsecurity/mng_guide.html",
            "reference_label": "経産省・IPA サイバーセキュリティ経営ガイドライン（関連ツール）"
          }
        },
        {
          "key": "B",
          "text": "可用性・性能・セキュリティ・運用性などの期待水準を合意し、スコープブレを防ぐ",
          "explanation": {
            "text": "非機能要件の明確化は品質期待値の共有とトラブル防止に直結する。",
            "reference": "https://www.meti.go.jp/policy/netsecurity/mng_guide.html",
            "reference_label": "経産省・IPA サイバーセキュリティ経営ガイドライン（関連ツール）"
          }
        },
        {
          "key": "C",
          "text": "契約形態が自動的に固定価格契約になる",
          "explanation": {
            "text": "契約形態は案件特性で決まり、非機能要件の記述が自動決定するものではない。",
            "reference": "https://www.meti.go.jp/policy/netsecurity/mng_guide.html",
            "reference_label": "経産省・IPA サイバーセキュリティ経営ガイドライン（関連ツール）"
          }
        },
        {
          "key": "D",
          "text": "技術選定に発注者が一切関与できなくなる",
          "explanation": {
            "text": "非機能要件は成果の期待値であり、関与を排除するものではない。",
            "reference": "https://www.meti.go.jp/policy/netsecurity/mng_guide.html",
            "reference_label": "経産省・IPA サイバーセキュリティ経営ガイドライン（関連ツール）"
          }
        }
      ],
      "answer": "B",
      "explanation": {
        "text": "RFPで非機能を明記すると品質・セキュリティ・可用性等の期待値が共有され、後工程の齟齬やリスクを抑制できる。",
        "reference": "https://www.meti.go.jp/policy/netsecurity/mng_guide.html",
        "reference_label": "経産省・IPA サイバーセキュリティ経営ガイドライン（関連ツール）"
      }
    },
    {
      "id": "it-ST-q28",
      "question": "経営としてのサイバーセキュリティの捉え方に関して、ガイドラインが求める経営者の行動として最も適切なものはどれか。",
      "difficulty": "normal",
      "choices": [
        {
          "key": "A",
          "text": "セキュリティはIT部門の専権事項とし、経営は関与しない",
          "explanation": {
            "text": "ガイドラインは経営課題としての関与と体制整備を求めている。",
            "reference": "https://www.meti.go.jp/policy/netsecurity/downloadfiles/guide_v3.0.pdf",
            "reference_label": "サイバーセキュリティ経営ガイドライン Ver3.0"
          }
        },
        {
          "key": "B",
          "text": "重要資産とリスクを特定し、優先順位と資源配分を主導する",
          "explanation": {
            "text": "経営者の責務として、リスクベースでの意思決定と資源確保を明示している。",
            "reference": "https://www.meti.go.jp/policy/netsecurity/downloadfiles/guide_v3.0.pdf",
            "reference_label": "サイバーセキュリティ経営ガイドライン Ver3.0"
          }
        },
        {
          "key": "C",
          "text": "CSIRTの技術手順書を経営者自ら詳細に執筆する",
          "explanation": {
            "text": "技術詳細は実務部門の役割で、経営は方針・資源・監督に注力する。",
            "reference": "https://www.meti.go.jp/policy/netsecurity/downloadfiles/guide_v3.0.pdf",
            "reference_label": "サイバーセキュリティ経営ガイドライン Ver3.0"
          }
        },
        {
          "key": "D",
          "text": "法令遵守は監査部門のみの責務であるとして任せる",
          "explanation": {
            "text": "法令遵守は経営の責任の下で全社的に推進すべき事項である。",
            "reference": "https://www.meti.go.jp/policy/netsecurity/downloadfiles/guide_v3.0.pdf",
            "reference_label": "サイバーセキュリティ経営ガイドライン Ver3.0"
          }
        }
      ],
      "answer": "B",
      "explanation": {
        "text": "ガイドラインは“経営者の責務”として重要資産・リスク把握、優先付け、体制・予算の確保、継続的改善を求めている。",
        "reference": "https://www.meti.go.jp/policy/netsecurity/downloadfiles/guide_v3.0.pdf",
        "reference_label": "サイバーセキュリティ経営ガイドライン Ver3.0"
      }
    },
    {
      "id": "it-ST-q29",
      "question": "ISMSに基づく情報資産管理において、重要度分類（機密性・完全性・可用性）を行う主な目的として最も適切なものはどれか。",
      "difficulty": "normal",
      "choices": [
        {
          "key": "A",
          "text": "資産ごとに最安値のクラウドを選ぶため",
          "explanation": {
            "text": "コスト最小化は副次的であり、ISMSの主目的ではない。",
            "reference": "https://www.ipa.go.jp/security/isec/jisq27001.html",
            "reference_label": "IPA ISMS関連解説（JIS Q 27001/27002の考え方）"
          }
        },
        {
          "key": "B",
          "text": "リスク評価と対策の優先順位付けの根拠を与えるため",
          "explanation": {
            "text": "機密性・完全性・可用性の要求度を明確にし、リスク対応の水準と優先度を決めるのが目的である。",
            "reference": "https://www.ipa.go.jp/security/isec/jisq27001.html",
            "reference_label": "IPA ISMS関連解説（JIS Q 27001/27002の考え方）"
          }
        },
        {
          "key": "C",
          "text": "在庫管理台帳の入力作業を簡素化するため",
          "explanation": {
            "text": "台帳簡素化は目的ではなく、リスクベースの管理が主眼である。",
            "reference": "https://www.ipa.go.jp/security/isec/jisq27001.html",
            "reference_label": "IPA ISMS関連解説（JIS Q 27001/27002の考え方）"
          }
        },
        {
          "key": "D",
          "text": "法的責任をクラウド事業者に移転するため",
          "explanation": {
            "text": "責任移転のための分類ではない。管理目的は組織のリスク低減である。",
            "reference": "https://www.ipa.go.jp/security/isec/jisq27001.html",
            "reference_label": "IPA ISMS関連解説（JIS Q 27001/27002の考え方）"
          }
        }
      ],
      "answer": "B",
      "explanation": {
        "text": "CIA特性に基づく重要度分類は、リスク評価とコントロール選定の基礎。要求度が高い資産ほど強固な対策を優先投入する。",
        "reference": "https://www.ipa.go.jp/security/isec/jisq27001.html",
        "reference_label": "IPA ISMS関連解説（JIS Q 27001/27002の考え方）"
      }
    },
    {
      "id": "it-ST-q30",
      "question": "ログ管理の戦略的目的として適切なものはどれか。",
      "difficulty": "normal",
      "choices": [
        {
          "key": "A",
          "text": "トラブル時の責任追及だけに用いること",
          "explanation": {
            "text": "追跡だけでなく、検知・抑止・証跡・監査・改善に資することが重要である。",
            "reference": "https://www.ipa.go.jp/security/pc/for_company/measure/monitor.html",
            "reference_label": "IPA セキュリティ対策（監視とログ活用の考え方）"
          }
        },
        {
          "key": "B",
          "text": "インシデント検知・原因分析・証跡確保・コンプライアンスの実現に活用すること",
          "explanation": {
            "text": "ログは検知から是正・監査までの全ライフサイクルで活用されるべきである。",
            "reference": "https://www.ipa.go.jp/security/pc/for_company/measure/monitor.html",
            "reference_label": "IPA セキュリティ対策（監視とログ活用の考え方）"
          }
        },
        {
          "key": "C",
          "text": "保存コスト削減のため最短期間で破棄すること",
          "explanation": {
            "text": "保存期間はリスクと要件で決める。短期破棄は証跡欠落のリスクを高める。",
            "reference": "https://www.ipa.go.jp/security/pc/for_company/measure/monitor.html",
            "reference_label": "IPA セキュリティ対策（監視とログ活用の考え方）"
          }
        },
        {
          "key": "D",
          "text": "個人情報を多く含めるほど有用性が高まる",
          "explanation": {
            "text": "最小権限・最小記録の原則と匿名化・マスキング等の配慮が必要である。",
            "reference": "https://www.ppc.go.jp/personalinfo/legal/",
            "reference_label": "個人情報保護委員会 法令・ガイドライン"
          }
        }
      ],
      "answer": "B",
      "explanation": {
        "text": "ログは“検知→分析→是正→監査”に通底する経営コントロールの材料。プライバシー配慮と保存要件の両立が鍵。",
        "reference": "https://www.ipa.go.jp/security/pc/for_company/measure/monitor.html",
        "reference_label": "IPA セキュリティ対策（監視とログ活用の考え方）"
      }
    },
    {
      "id": "it-ST-q31",
      "question": "クラウド利用における暗号鍵管理（KMS等）で、利用者側が留意すべき点として最も適切なものはどれか。",
      "difficulty": "hard",
      "choices": [
        {
          "key": "A",
          "text": "クラウド事業者のデフォルト設定に従えば鍵のローテーションは不要",
          "explanation": {
            "text": "鍵のライフサイクル管理（生成・配布・ローテーション・失効）は利用者の責任領域を含む。",
            "reference": "https://www.ipa.go.jp/security/cloud/guide.html",
            "reference_label": "IPA クラウドセキュリティガイド（責任共有・暗号管理）"
          }
        },
        {
          "key": "B",
          "text": "鍵保護の強度、アクセス制御、監査証跡、ローテーション方針を定義し、BYOK等の採否もリスクベースで決める",
          "explanation": {
            "text": "暗号鍵の管理は技術・運用・権限・証跡を統合的に設計し、共有責任の自社側分担を明確にする必要がある。",
            "reference": "https://www.ipa.go.jp/security/cloud/guide.html",
            "reference_label": "IPA クラウドセキュリティガイド（責任共有・暗号管理）"
          }
        },
        {
          "key": "C",
          "text": "鍵は一つに統一し、全システムで共用すると運用が簡単",
          "explanation": {
            "text": "鍵の共用は侵害時の影響範囲を拡大する。分離・最小権限が原則である。",
            "reference": "https://www.ipa.go.jp/security/cloud/guide.html",
            "reference_label": "IPA クラウドセキュリティガイド（責任共有・暗号管理）"
          }
        },
        {
          "key": "D",
          "text": "鍵管理は事業者責任なので利用者側の監査は不要",
          "explanation": {
            "text": "IaaS/PaaS/SaaSいずれも利用者側の設定・監査責務が残る。",
            "reference": "https://www.ipa.go.jp/security/cloud/guide.html",
            "reference_label": "IPA クラウドセキュリティガイド（責任共有・暗号管理）"
          }
        }
      ],
      "answer": "B",
      "explanation": {
        "text": "暗号鍵管理は共有責任。強固な保護とアクセス管理、証跡、ローテーションを整備し、BYOK/ホスト型の選択もリスクで判断する。",
        "reference": "https://www.ipa.go.jp/security/cloud/guide.html",
        "reference_label": "IPA クラウドセキュリティガイド（責任共有・暗号管理）"
      }
    },
    {
      "id": "it-ST-q32",
      "question": "個人情報保護法における「外国にある第三者への提供」に関する適切な説明はどれか。",
      "difficulty": "hard",
      "choices": [
        {
          "key": "A",
          "text": "国外提供であっても本人同意や十分性認定・体制整備等の要件は不要",
          "explanation": {
            "text": "国外提供には、同意・十分性認定・体制整備等の要件が求められる。",
            "reference": "https://www.ppc.go.jp/personalinfo/legal/kaisei/",
            "reference_label": "個人情報保護委員会 改正法の概要（外国第三者提供）"
          }
        },
        {
          "key": "B",
          "text": "提供先国の制度や体制、適切な体制整備（契約等）または本人同意などの条件を満たす必要がある",
          "explanation": {
            "text": "国外移転の際は、相手国制度の確認や適切な体制整備、本人同意等のいずれかの要件充足が必要。",
            "reference": "https://www.ppc.go.jp/personalinfo/legal/kaisei/",
            "reference_label": "個人情報保護委員会 改正法の概要（外国第三者提供）"
          }
        },
        {
          "key": "C",
          "text": "クラウド上の保管は『提供』に該当しないため一切の配慮は不要",
          "explanation": {
            "text": "取扱いは具体的態様により判断され、国外の事業者関与があれば要件確認が必要となる場合がある。",
            "reference": "https://www.ppc.go.jp/personalinfo/legal/kaisei/",
            "reference_label": "個人情報保護委員会 改正法の概要（外国第三者提供）"
          }
        },
        {
          "key": "D",
          "text": "匿名加工情報に該当すれば必ず本人同意が必要",
          "explanation": {
            "text": "匿名加工情報は特別な公表義務等の枠組みで運用され、本人同意の要否は仮名・匿名の区分で異なる。",
            "reference": "https://www.ppc.go.jp/personalinfo/legal/guidelines_anonymous/",
            "reference_label": "個人情報保護委員会 ガイドライン（仮名・匿名加工情報）"
          }
        }
      ],
      "answer": "B",
      "explanation": {
        "text": "国外第三者提供では、相手国の個人情報保護制度の水準や、契約等による適切な体制整備、または本人同意などの要件を満たす必要がある。",
        "reference": "https://www.ppc.go.jp/personalinfo/legal/kaisei/",
        "reference_label": "個人情報保護委員会 改正法の概要（外国第三者提供）"
      }
    },
    {
      "id": "it-ST-q33",
      "question": "生成AIの業務利用における著作権上の留意点として、文化庁の考え方に最も整合するものはどれか。",
      "difficulty": "hard",
      "choices": [
        {
          "key": "A",
          "text": "学習用データの収集はすべて著作権侵害に当たる",
          "explanation": {
            "text": "著作権法30条の4など、一定の条件下で許容される場合があると整理されている。",
            "reference": "https://www.bunka.go.jp/seisaku/chosakuken/ai/",
            "reference_label": "文化庁 AIと著作権に関する考え方"
          }
        },
        {
          "key": "B",
          "text": "生成物の利用に伴う権利侵害リスク（類似性・商標・肖像等）や機密情報流出に配慮し、社内ルールで検証・出典管理を行う",
          "explanation": {
            "text": "生成物の二次利用・商用利用には権利・秘密情報の観点からの検証・管理が必要とされる。",
            "reference": "https://www.bunka.go.jp/seisaku/chosakuken/ai/",
            "reference_label": "文化庁 AIと著作権に関する考え方"
          }
        },
        {
          "key": "C",
          "text": "生成AIの出力はすべて著作物に該当するため自由に独占できる",
          "explanation": {
            "text": "生成物の著作物性や帰属は個別事情に依存し、一律の取扱いではない。",
            "reference": "https://www.bunka.go.jp/seisaku/chosakuken/ai/",
            "reference_label": "文化庁 AIと著作権に関する考え方"
          }
        },
        {
          "key": "D",
          "text": "プロンプトに第三者の機密情報を入力しても法的問題は生じない",
          "explanation": {
            "text": "秘密情報・個人情報の入力は情報管理上の重大なリスクとなる。",
            "reference": "https://www.ipa.go.jp/ikc/reports/ai/ai-governance.html",
            "reference_label": "IPA AIガバナンス"
          }
        }
      ],
      "answer": "B",
      "explanation": {
        "text": "文化庁はAIと著作権の整理を示しており、業務利用では権利侵害・秘密情報流出等のリスク管理と社内ルール化が不可欠とされる。",
        "reference": "https://www.bunka.go.jp/seisaku/chosakuken/ai/",
        "reference_label": "文化庁 AIと著作権に関する考え方"
      }
    },
    {
      "id": "it-ST-q34",
      "question": "EA移行計画（To-Be実現）で、老朽システム群を安全に刷新する方策として最も適切なものはどれか。",
      "difficulty": "normal",
      "choices": [
        {
          "key": "A",
          "text": "全システムを一斉に切替えるビッグバン移行を第一選択とする",
          "explanation": {
            "text": "影響範囲とリスクが極大化し、EAの全体最適にも反する場合が多い。",
            "reference": "https://www.ipa.go.jp/ea/index.html",
            "reference_label": "IPA エンタープライズ・アーキテクチャ"
          }
        },
        {
          "key": "B",
          "text": "業務優先度と依存関係に基づく段階的移行（ストラングラーパターン等）を計画し、現行とTo-Beの乖離を可視化して管理する",
          "explanation": {
            "text": "EAは現行/目標/移行の整合管理が本質。段階的移行はリスクを抑え学習を得ながら進められる。",
            "reference": "https://www.ipa.go.jp/ea/index.html",
            "reference_label": "IPA エンタープライズ・アーキテクチャ"
          }
        },
        {
          "key": "C",
          "text": "現行システムの課題は無視し、To-Be図だけを作成する",
          "explanation": {
            "text": "As-Isの把握と乖離管理がなければ実効性のある移行は設計できない。",
            "reference": "https://www.ipa.go.jp/ea/index.html",
            "reference_label": "IPA エンタープライズ・アーキテクチャ"
          }
        },
        {
          "key": "D",
          "text": "影響分析を簡略化するために依存関係の把握は後回しにする",
          "explanation": {
            "text": "依存関係の管理は移行の核心であり、後回しは重大リスクとなる。",
            "reference": "https://www.ipa.go.jp/ea/index.html",
            "reference_label": "IPA エンタープライズ・アーキテクチャ"
          }
        }
      ],
      "answer": "B",
      "explanation": {
        "text": "EAではAs-Is/To-Be/移行計画を統合管理する。段階的移行で依存関係と優先度を踏まえ、リスクを制御しながら刷新するのが定石。",
        "reference": "https://www.ipa.go.jp/ea/index.html",
        "reference_label": "IPA エンタープライズ・アーキテクチャ"
      }
    },
    {
      "id": "it-ST-q35",
      "question": "脆弱性対策において、JVNやJVN iPedia等の情報を活用する主目的として最も適切なものはどれか。",
      "difficulty": "easy",
      "choices": [
        {
          "key": "A",
          "text": "ベンダーの広報文を引用するため",
          "explanation": {
            "text": "目的は広報転載ではなく、信頼できる脆弱性情報の収集と対策適用である。",
            "reference": "https://jvndb.jvn.jp/",
            "reference_label": "IPA JVN iPedia 脆弱性対策情報データベース"
          }
        },
        {
          "key": "B",
          "text": "製品・バージョンごとの脆弱性情報を網羅的に把握し、優先度付けと対処（パッチ適用・緩和策）に反映する",
          "explanation": {
            "text": "JVN/JVN iPediaはCVE等と連携して脆弱性情報を提供し、迅速な対処判断に資する。",
            "reference": "https://jvndb.jvn.jp/",
            "reference_label": "IPA JVN iPedia 脆弱性対策情報データベース"
          }
        },
        {
          "key": "C",
          "text": "法的に必ず全ての脆弱性を即日修正するため",
          "explanation": {
            "text": "優先順位付けとリスク評価に基づく対応が現実的である。",
            "reference": "https://jvndb.jvn.jp/",
            "reference_label": "IPA JVN iPedia 脆弱性対策情報データベース"
          }
        },
        {
          "key": "D",
          "text": "脆弱性の存在を外部に周知し、攻撃を誘発するため",
          "explanation": {
            "text": "目的は適切な注意喚起と対策促進であり、攻撃誘発ではない。",
            "reference": "https://jvndb.jvn.jp/",
            "reference_label": "IPA JVN iPedia 脆弱性対策情報データベース"
          }
        }
      ],
      "answer": "B",
      "explanation": {
        "text": "JVN/JVN iPediaは国内の信頼できる脆弱性情報源。資産棚卸と組み合せ、影響製品の特定と優先度付け、パッチ/緩和策の実施につなげる。",
        "reference": "https://jvndb.jvn.jp/",
        "reference_label": "IPA JVN iPedia 脆弱性対策情報データベース"
      }
    },
    {
      "id": "it-ST-q36",
      "question": "データ匿名化の設計で最も重要な考慮点はどれか。",
      "difficulty": "hard",
      "choices": [
        {
          "key": "A",
          "text": "匿名化後のデータは完全に復元可能であること",
          "explanation": {
            "text": "匿名化の目的は識別性を低減することであり、復元可能であるなら匿名化の意味がない。",
            "reference": "https://www.ppc.go.jp/personalinfo/legal/guidelines_anonymous/",
            "reference_label": "個人情報保護委員会 ガイドライン（匿名加工情報）"
          }
        },
        {
          "key": "B",
          "text": "再識別リスクと利用目的のバランスを取り、適切な加工方法を選択すること",
          "explanation": {
            "text": "匿名化は有用性と保護の両立が必要で、リスク評価と目的適合性が核心となる。",
            "reference": "https://www.ppc.go.jp/personalinfo/legal/guidelines_anonymous/",
            "reference_label": "個人情報保護委員会 ガイドライン（匿名加工情報）"
          }
        },
        {
          "key": "C",
          "text": "匿名化すれば常に第三者提供が無条件で可能になること",
          "explanation": {
            "text": "匿名加工情報には第三者提供時の公表義務などが残る。無条件利用は誤り。",
            "reference": "https://www.ppc.go.jp/personalinfo/legal/guidelines_anonymous/",
            "reference_label": "個人情報保護委員会 ガイドライン（匿名加工情報）"
          }
        },
        {
          "key": "D",
          "text": "匿名化の方法は事業者の恣意で決めればよい",
          "explanation": {
            "text": "指針に基づいた合理的な方法を採用する必要がある。",
            "reference": "https://www.ppc.go.jp/personalinfo/legal/guidelines_anonymous/",
            "reference_label": "個人情報保護委員会 ガイドライン（匿名加工情報）"
          }
        }
      ],
      "answer": "B",
      "explanation": {
        "text": "匿名化設計の要諦は“有用性と保護のバランス”。再識別リスクを評価し、利用目的に応じた加工を行うことが求められる。",
        "reference": "https://www.ppc.go.jp/personalinfo/legal/guidelines_anonymous/",
        "reference_label": "個人情報保護委員会 ガイドライン（匿名加工情報）"
      }
    },
    {
      "id": "it-ST-q37",
      "question": "AIの説明可能性（Explainability）が重視される理由として適切なものはどれか。",
      "difficulty": "normal",
      "choices": [
        {
          "key": "A",
          "text": "モデルの精度を落とすため",
          "explanation": {
            "text": "説明可能性は精度を落とすことが目的ではない。",
            "reference": "https://www.ipa.go.jp/ikc/reports/ai/ai-governance.html",
            "reference_label": "IPA AIガバナンス"
          }
        },
        {
          "key": "B",
          "text": "意思決定根拠の透明性を確保し、責任所在を明確にするため",
          "explanation": {
            "text": "AIガバナンスでは説明責任と透明性が重要とされる。",
            "reference": "https://www.ipa.go.jp/ikc/reports/ai/ai-governance.html",
            "reference_label": "IPA AIガバナンス"
          }
        },
        {
          "key": "C",
          "text": "利用者の直感に基づいた判断を補強するため",
          "explanation": {
            "text": "説明可能性は直感補強ではなく、透明性・公平性確保の観点から求められる。",
            "reference": "https://www.ipa.go.jp/ikc/reports/ai/ai-governance.html",
            "reference_label": "IPA AIガバナンス"
          }
        },
        {
          "key": "D",
          "text": "AIが出力する結果を無条件に信頼できるようにするため",
          "explanation": {
            "text": "説明可能性は無条件信頼を目的とせず、むしろ結果検証の基盤を与える。",
            "reference": "https://www.ipa.go.jp/ikc/reports/ai/ai-governance.html",
            "reference_label": "IPA AIガバナンス"
          }
        }
      ],
      "answer": "B",
      "explanation": {
        "text": "説明可能性は、透明性・責任所在・利用者への説明責任を担保するために求められる。",
        "reference": "https://www.ipa.go.jp/ikc/reports/ai/ai-governance.html",
        "reference_label": "IPA AIガバナンス"
      }
    },
    {
      "id": "it-ST-q38",
      "question": "クラウド事業者の第三者保証報告書（SOC2等）を利用する主な目的はどれか。",
      "difficulty": "normal",
      "choices": [
        {
          "key": "A",
          "text": "クラウドの利用料金が妥当かを検証するため",
          "explanation": {
            "text": "SOC2は料金ではなく、統制の有効性を対象とする。",
            "reference": "https://www.ipa.go.jp/security/cloud/guide.html",
            "reference_label": "IPA クラウドセキュリティガイド"
          }
        },
        {
          "key": "B",
          "text": "サービス提供者の内部統制やセキュリティ管理の有効性を第三者証明で確認するため",
          "explanation": {
            "text": "SOC2等は外部保証により利用者が統制有効性を確認する材料となる。",
            "reference": "https://www.ipa.go.jp/security/cloud/guide.html",
            "reference_label": "IPA クラウドセキュリティガイド"
          }
        },
        {
          "key": "C",
          "text": "契約条件を強制的に変更させるため",
          "explanation": {
            "text": "保証報告書は監査証跡であり、契約変更を強制するものではない。",
            "reference": "https://www.ipa.go.jp/security/cloud/guide.html",
            "reference_label": "IPA クラウドセキュリティガイド"
          }
        },
        {
          "key": "D",
          "text": "利用者が内部統制の監査を免除されるため",
          "explanation": {
            "text": "利用者側の責任共有は残る。免除を意味しない。",
            "reference": "https://www.ipa.go.jp/security/cloud/guide.html",
            "reference_label": "IPA クラウドセキュリティガイド"
          }
        }
      ],
      "answer": "B",
      "explanation": {
        "text": "SOC2等はクラウド事業者の統制の有効性を第三者が保証する報告書であり、利用者がリスク評価・監査の一部に活用できる。",
        "reference": "https://www.ipa.go.jp/security/cloud/guide.html",
        "reference_label": "IPA クラウドセキュリティガイド"
      }
    },
    {
      "id": "it-ST-q39",
      "question": "インシデント対応体制（CSIRT/PSIRT）の役割として最も適切なものはどれか。",
      "difficulty": "easy",
      "choices": [
        {
          "key": "A",
          "text": "全てのセキュリティ対応を外部ベンダーに委託すること",
          "explanation": {
            "text": "CSIRT/PSIRTは組織内部で体制を構築し、外部連携も行う。",
            "reference": "https://www.ipa.go.jp/security/csirt/index.html",
            "reference_label": "IPA CSIRT関連情報"
          }
        },
        {
          "key": "B",
          "text": "インシデント検知・対応・分析・報告を行い、組織の対応力を強化すること",
          "explanation": {
            "text": "CSIRT/PSIRTは組織的なインシデント対応の中心機能を担う。",
            "reference": "https://www.ipa.go.jp/security/csirt/index.html",
            "reference_label": "IPA CSIRT関連情報"
          }
        },
        {
          "key": "C",
          "text": "セキュリティ対応は経営の課題ではないと宣言すること",
          "explanation": {
            "text": "インシデント対応は経営課題であり、体制構築は経営主導で行うべき。",
            "reference": "https://www.ipa.go.jp/security/csirt/index.html",
            "reference_label": "IPA CSIRT関連情報"
          }
        },
        {
          "key": "D",
          "text": "ログを保存しない方針を定めること",
          "explanation": {
            "text": "ログ保全は対応・原因分析に不可欠であり、保存しないのは誤り。",
            "reference": "https://www.ipa.go.jp/security/csirt/index.html",
            "reference_label": "IPA CSIRT関連情報"
          }
        }
      ],
      "answer": "B",
      "explanation": {
        "text": "CSIRT/PSIRTはインシデント対応を組織的に担い、検知・分析・復旧・改善を統括する体制である。",
        "reference": "https://www.ipa.go.jp/security/csirt/index.html",
        "reference_label": "IPA CSIRT関連情報"
      }
    },
    {
      "id": "it-ST-q40",
      "question": "外部委託先管理におけるセキュリティガバナンスの観点で最も適切なものはどれか。",
      "difficulty": "normal",
      "choices": [
        {
          "key": "A",
          "text": "契約後は委託先のセキュリティを監査せずに信頼する",
          "explanation": {
            "text": "委託先管理は契約後もモニタリング・監査が必要である。",
            "reference": "https://www.ipa.go.jp/security/outsourcing/index.html",
            "reference_label": "IPA 委託先管理に関する指針"
          }
        },
        {
          "key": "B",
          "text": "委託契約にセキュリティ要求を盛込み、定期的に監査・モニタリングを行う",
          "explanation": {
            "text": "契約・監査・改善のサイクルを回すことがガバナンスの基本である。",
            "reference": "https://www.ipa.go.jp/security/outsourcing/index.html",
            "reference_label": "IPA 委託先管理に関する指針"
          }
        },
        {
          "key": "C",
          "text": "契約時に一度だけセキュリティチェックを行えば十分",
          "explanation": {
            "text": "契約時だけでなく、継続的なモニタリングが必要である。",
            "reference": "https://www.ipa.go.jp/security/outsourcing/index.html",
            "reference_label": "IPA 委託先管理に関する指針"
          }
        },
        {
          "key": "D",
          "text": "委託先が海外の場合は一切の責任を免れる",
          "explanation": {
            "text": "委託先が国内外を問わず責任は発注者側にも残る。",
            "reference": "https://www.ipa.go.jp/security/outsourcing/index.html",
            "reference_label": "IPA 委託先管理に関する指針"
          }
        }
      ],
      "answer": "B",
      "explanation": {
        "text": "外部委託管理は契約に要求を盛込み、監査と改善を継続することで実効性を確保する。",
        "reference": "https://www.ipa.go.jp/security/outsourcing/index.html",
        "reference_label": "IPA 委託先管理に関する指針"
      }
    },
    {
      "id": "it-ST-q41",
      "question": "SLAで可用性99.9%を定義した場合、事業側で定めるRTOとの整合性を確認する理由はどれか。",
      "difficulty": "normal",
      "choices": [
        {
          "key": "A",
          "text": "SLAがあればRTOの定義は不要だから",
          "explanation": {
            "text": "SLAは事業要求とは別に定義されるため、RTOを省略することはできない。",
            "reference": "https://www.ipa.go.jp/security/bcm/index.html",
            "reference_label": "IPA 事業継続とIT"
          }
        },
        {
          "key": "B",
          "text": "SLAの可用性指標が事業継続上の許容停止時間（RTO）を満たすかを確認するため",
          "explanation": {
            "text": "SLAが満たされてもRTOを超える停止時間が発生すれば事業は継続できない可能性があるため、整合確認が必要。",
            "reference": "https://www.ipa.go.jp/security/bcm/index.html",
            "reference_label": "IPA 事業継続とIT"
          }
        },
        {
          "key": "C",
          "text": "RTOを定めるとペナルティが自動的に免除されるため",
          "explanation": {
            "text": "RTOは事業要求指標であり、ペナルティ免除の仕組みではない。",
            "reference": "https://www.ipa.go.jp/security/bcm/index.html",
            "reference_label": "IPA 事業継続とIT"
          }
        },
        {
          "key": "D",
          "text": "SLAとRTOは全く無関係だから整合性確認は不要",
          "explanation": {
            "text": "両者は関連し、整合性を欠くと事業に影響を与える。",
            "reference": "https://www.ipa.go.jp/security/bcm/index.html",
            "reference_label": "IPA 事業継続とIT"
          }
        }
      ],
      "answer": "B",
      "explanation": {
        "text": "SLAの可用性とRTOは別の指標だが、両者が整合して初めて事業継続要件を満たせる。整合性確認は必須。",
        "reference": "https://www.ipa.go.jp/security/bcm/index.html",
        "reference_label": "IPA 事業継続とIT"
      }
    },
    {
      "id": "it-ST-q42",
      "question": "ベネフィット・マネジメントの目的として最も適切なものはどれか。",
      "difficulty": "easy",
      "choices": [
        {
          "key": "A",
          "text": "IT投資のROIを短期的に最大化することのみを狙う",
          "explanation": {
            "text": "短期ROIだけに偏るのではなく、持続的な成果・価値実現を重視する。",
            "reference": "https://www.ipa.go.jp/ikc/reports/it_management/benefit.html",
            "reference_label": "IPA IT投資ベネフィット・マネジメント"
          }
        },
        {
          "key": "B",
          "text": "投資から得られる成果・便益を特定し、その実現・測定・最大化を組織的に管理すること",
          "explanation": {
            "text": "ベネフィット・マネジメントは成果を特定し、測定・実現を追跡する枠組みである。",
            "reference": "https://www.ipa.go.jp/ikc/reports/it_management/benefit.html",
            "reference_label": "IPA IT投資ベネフィット・マネジメント"
          }
        },
        {
          "key": "C",
          "text": "ITシステム導入後の利用状況を無視し、計画段階の投資額のみで判断すること",
          "explanation": {
            "text": "導入後の成果測定と追跡を行わなければ価値実現を保証できない。",
            "reference": "https://www.ipa.go.jp/ikc/reports/it_management/benefit.html",
            "reference_label": "IPA IT投資ベネフィット・マネジメント"
          }
        },
        {
          "key": "D",
          "text": "成果は定性的に把握すれば十分であり、定量的測定は不要とすること",
          "explanation": {
            "text": "便益の実現度を把握するためには定性的評価だけでなく定量的測定が必要。",
            "reference": "https://www.ipa.go.jp/ikc/reports/it_management/benefit.html",
            "reference_label": "IPA IT投資ベネフィット・マネジメント"
          }
        }
      ],
      "answer": "B",
      "explanation": {
        "text": "ベネフィット・マネジメントは、IT投資から得られる便益を特定し、測定・実現・改善を行うことで、経営戦略と整合した価値を最大化する仕組みである。",
        "reference": "https://www.ipa.go.jp/ikc/reports/it_management/benefit.html",
        "reference_label": "IPA IT投資ベネフィット・マネジメント"
      }
    },
    {
      "id": "it-ST-q43",
      "question": "ITストラテジストがまず優先して担うべき役割として最も適切なものはどれか。",
      "difficulty": "normal",
      "choices": [
        {
          "key": "A",
          "text": "個別システムの詳細設計レビューだけに専念する",
          "explanation": {
            "text": "詳細設計レビューは重要だが、ストラテジストの主務は経営戦略とIT戦略の整合と全体最適の推進にある。",
            "reference": "https://www.ipa.go.jp/shiken/syllabus/gaiyou.html",
            "reference_label": "IPA 試験シラバス（ITストラテジスト Ver.4.2）"
          }
        },
        {
          "key": "B",
          "text": "経営戦略と整合したIT戦略の立案とポートフォリオ最適化を主導する",
          "explanation": {
            "text": "シラバスは経営戦略との整合・IT投資の最適化・ITガバナンスを中核能力として定義している。",
            "reference": "https://www.ipa.go.jp/shiken/syllabus/gaiyou.html",
            "reference_label": "IPA 試験シラバス（ITストラテジスト Ver.4.2）"
          }
        },
        {
          "key": "C",
          "text": "最新技術の導入件数を増やすことのみをKPIとする",
          "explanation": {
            "text": "技術導入は手段であり、経営価値や成果（ベネフィット）との整合が必要。",
            "reference": "https://www.ipa.go.jp/shiken/syllabus/gaiyou.html",
            "reference_label": "IPA 試験シラバス（ITストラテジスト Ver.4.2）"
          }
        },
        {
          "key": "D",
          "text": "IT部門だけで完結する目標を設定し全社調整は行わない",
          "explanation": {
            "text": "全社最適とステークホルダー調整がストラテジストの必須職責。",
            "reference": "https://www.ipa.go.jp/shiken/syllabus/gaiyou.html",
            "reference_label": "IPA 試験シラバス（ITストラテジスト Ver.4.2）"
          }
        }
      ],
      "answer": "B",
      "explanation": {
        "text": "ITストラテジストは経営戦略と整合したIT戦略を描き、投資ポートフォリオやガバナンスを通じて全体最適を実現する役割が本質である。",
        "reference": "https://www.ipa.go.jp/shiken/syllabus/gaiyou.html",
        "reference_label": "IPA 試験シラバス（ITストラテジスト Ver.4.2）"
      }
    },
    {
      "id": "it-ST-q44",
      "question": "サプライチェーンのサイバーリスク対応で、経営者の責務として最も適切なものはどれか。",
      "difficulty": "normal",
      "choices": [
        {
          "key": "A",
          "text": "委託先のセキュリティは各部門に任せ、経営としての指針は示さない",
          "explanation": {
            "text": "経営ガイドラインは経営者の関与と体制整備、優先順位付けを求めている。",
            "reference": "https://www.meti.go.jp/policy/netsecurity/downloadfiles/guide_v3.0.pdf",
            "reference_label": "サイバーセキュリティ経営ガイドライン Ver3.0"
          }
        },
        {
          "key": "B",
          "text": "重要資産・重要取引先を特定し、要求事項を契約に反映、モニタリングと改善を指示する",
          "explanation": {
            "text": "経営者は重要資産・リスク把握、要求事項の明確化、体制・資源確保、継続的改善を主導する責務がある。",
            "reference": "https://www.meti.go.jp/policy/netsecurity/downloadfiles/guide_v3.0.pdf",
            "reference_label": "サイバーセキュリティ経営ガイドライン Ver3.0"
          }
        },
        {
          "key": "C",
          "text": "委託先が海外であればリスクは自動的に移転される",
          "explanation": {
            "text": "委託の有無や所在地に関わらず発注者責任は残る。",
            "reference": "https://www.meti.go.jp/policy/netsecurity/downloadfiles/guide_v3.0.pdf",
            "reference_label": "サイバーセキュリティ経営ガイドライン Ver3.0"
          }
        },
        {
          "key": "D",
          "text": "監査や報告は任意でよく、継続的モニタリングは不要",
          "explanation": {
            "text": "継続的な確認・改善が求められている。",
            "reference": "https://www.meti.go.jp/policy/netsecurity/downloadfiles/guide_v3.0.pdf",
            "reference_label": "サイバーセキュリティ経営ガイドライン Ver3.0"
          }
        }
      ],
      "answer": "B",
      "explanation": {
        "text": "ガイドラインは経営のリーダーシップの下で、サプライチェーンを含むリスクの把握・契約要求・モニタリング・改善までを求めている。",
        "reference": "https://www.meti.go.jp/policy/netsecurity/downloadfiles/guide_v3.0.pdf",
        "reference_label": "サイバーセキュリティ経営ガイドライン Ver3.0"
      }
    },
    {
      "id": "it-ST-q45",
      "question": "クラウドの責任共有モデルにおいて、SaaS利用時に利用者（顧客）が主として担う責任として適切なものはどれか。",
      "difficulty": "easy",
      "choices": [
        {
          "key": "A",
          "text": "データセンタの電源・空調の保守",
          "explanation": {
            "text": "物理層はサービス事業者側の責任である。",
            "reference": "https://www.ipa.go.jp/jinzai/ics/core_human_resource/final_project/2024/cloud-security.html",
            "reference_label": "IPA クラウドセキュリティの歩き方（責任共有の整理）"
          }
        },
        {
          "key": "B",
          "text": "アカウント・認証設定、権限管理、データ分類・バックアップ方針、端末側の安全対策",
          "explanation": {
            "text": "SaaSでもID/アクセス、データ保護、エンドポイント等は利用者の重要責任領域として残る。",
            "reference": "https://www.ipa.go.jp/jinzai/ics/core_human_resource/final_project/2024/cloud-security.html",
            "reference_label": "IPA クラウドセキュリティの歩き方（責任共有の整理）"
          }
        },
        {
          "key": "C",
          "text": "SaaSのソースコード修正とリリース管理",
          "explanation": {
            "text": "アプリケーションの内部実装はSaaS提供者側の責任である。",
            "reference": "https://www.ipa.go.jp/jinzai/ics/core_human_resource/final_project/2024/cloud-security.html",
            "reference_label": "IPA クラウドセキュリティの歩き方（責任共有の整理）"
          }
        },
        {
          "key": "D",
          "text": "データセンタ立入者の入退管理",
          "explanation": {
            "text": "物理的入退室管理は事業者側の統制に属する。",
            "reference": "https://www.ipa.go.jp/jinzai/ics/core_human_resource/final_project/2024/cloud-security.html",
            "reference_label": "IPA クラウドセキュリティの歩き方（責任共有の整理）"
          }
        }
      ],
      "answer": "B",
      "explanation": {
        "text": "SaaSでは基盤とアプリは事業者責任が中心だが、ID管理やデータ保護、端末など“利用者側設定”の良否が全体リスクに直結する。",
        "reference": "https://www.ipa.go.jp/jinzai/ics/core_human_resource/final_project/2024/cloud-security.html",
        "reference_label": "IPA クラウドセキュリティの歩き方（責任共有の整理）"
      }
    },
    {
      "id": "it-ST-q46",
      "question": "個人情報の国外第三者提供に関する説明として適切なものはどれか。",
      "difficulty": "hard",
      "choices": [
        {
          "key": "A",
          "text": "国外提供であれば本人同意や体制整備は不要である",
          "explanation": {
            "text": "国外提供には同意、十分性認定、適切な体制整備（契約等）のいずれかの要件が求められる。",
            "reference": "https://www.ppc.go.jp/personalinfo/legal/kaisei/",
            "reference_label": "個人情報保護委員会 改正法の概要（外国第三者提供）"
          }
        },
        {
          "key": "B",
          "text": "提供先の制度・体制の確認や契約等による適切な体制整備、または本人同意などの条件を満たす必要がある",
          "explanation": {
            "text": "国外第三者提供では、十分性認定国や契約による体制整備、本人同意などの要件充足が必要と整理されている。",
            "reference": "https://www.ppc.go.jp/personalinfo/legal/kaisei/",
            "reference_label": "個人情報保護委員会 改正法の概要（外国第三者提供）"
          }
        },
        {
          "key": "C",
          "text": "クラウドに保存するだけなら常に国外提供に当たらない",
          "explanation": {
            "text": "具体的な取扱い態様により判断される。国外の事業者関与等があれば要件確認が必要な場合がある。",
            "reference": "https://www.ppc.go.jp/personalinfo/legal/kaisei/",
            "reference_label": "個人情報保護委員会 改正法の概要（外国第三者提供）"
          }
        },
        {
          "key": "D",
          "text": "匿名加工情報であっても必ず本人同意が必要である",
          "explanation": {
            "text": "匿名加工情報は非復元性を要件とする枠組みで、公表等の義務が中心。常に同意が必要とは限らない。",
            "reference": "https://www.ppc.go.jp/personalinfo/legal/guidelines_anonymous/",
            "reference_label": "個人情報保護委員会 ガイドライン（仮名・匿名加工情報）"
          }
        }
      ],
      "answer": "B",
      "explanation": {
        "text": "国外第三者提供は相手国制度や契約等による適切な体制整備、または本人同意などを満たすことが要件となる。",
        "reference": "https://www.ppc.go.jp/personalinfo/legal/kaisei/",
        "reference_label": "個人情報保護委員会 改正法の概要（外国第三者提供）"
      }
    },
    {
      "id": "it-ST-q47",
      "question": "インシデント対応力を高めるうえで、事前に最も効果的とされる取組はどれか。",
      "difficulty": "normal",
      "choices": [
        {
          "key": "A",
          "text": "インシデント発生時に考える方針で十分とし、平時の演習は行わない",
          "explanation": {
            "text": "ガイドラインは平時の体制整備・訓練・演習の重要性を強調している。",
            "reference": "https://www.meti.go.jp/policy/netsecurity/mng_guide.html",
            "reference_label": "経産省・IPA サイバーセキュリティ経営ガイドライン（支援ツール）"
          }
        },
        {
          "key": "B",
          "text": "机上演習（Tabletop）や技術演習を定期実施し、責任・連絡経路・判断基準を確認する",
          "explanation": {
            "text": "演習は実効性ある対応の鍵で、役割・連絡・判断の確認に資する。",
            "reference": "https://www.meti.go.jp/policy/netsecurity/mng_guide.html",
            "reference_label": "経産省・IPA サイバーセキュリティ経営ガイドライン（支援ツール）"
          }
        },
        {
          "key": "C",
          "text": "対応はベンダ任せとし、自社に連絡体制は置かない",
          "explanation": {
            "text": "組織内体制（CSIRT等）の整備が前提であり、丸投げは不適切。",
            "reference": "https://www.meti.go.jp/policy/netsecurity/mng_guide.html",
            "reference_label": "経産省・IPA サイバーセキュリティ経営ガイドライン（支援ツール）"
          }
        },
        {
          "key": "D",
          "text": "ログは保存しない方が漏えいリスクが減るので有効である",
          "explanation": {
            "text": "証跡がなければ検知・分析・再発防止が困難となる。",
            "reference": "https://www.meti.go.jp/policy/netsecurity/mng_guide.html",
            "reference_label": "経産省・IPA サイバーセキュリティ経営ガイドライン（支援ツール）"
          }
        }
      ],
      "answer": "B",
      "explanation": {
        "text": "平時の計画・訓練・演習により、役割・連絡・判断を確認しておくことが、組織のインシデント対応力を大きく左右する。",
        "reference": "https://www.meti.go.jp/policy/netsecurity/mng_guide.html",
        "reference_label": "経産省・IPA サイバーセキュリティ経営ガイドライン（支援ツール）"
      }
    },
    {
      "id": "it-ST-q48",
      "question": "生成AIの企業利用におけるガバナンスとして最も適切なものはどれか。",
      "difficulty": "hard",
      "choices": [
        {
          "key": "A",
          "text": "出力は常に正しい前提で、そのまま顧客向け資料に使用する",
          "explanation": {
            "text": "AI出力には誤りや権利侵害リスクがあり、検証・責任の明確化が必要とされる。",
            "reference": "https://www.ipa.go.jp/ikc/reports/ai/ai-governance.html",
            "reference_label": "IPA AIガバナンス"
          }
        },
        {
          "key": "B",
          "text": "入力データの取り扱いルール、出力検証プロセス、著作権・個人情報等のリスク管理、ログ・出典記録を整備する",
          "explanation": {
            "text": "透明性・説明責任・権利/プライバシー配慮を満たすルール整備が求められている。",
            "reference": "https://www.ipa.go.jp/ikc/reports/ai/ai-governance.html",
            "reference_label": "IPA AIガバナンス"
          }
        },
        {
          "key": "C",
          "text": "部門ごとに独自ルールで運用し、全社基準は設けない",
          "explanation": {
            "text": "全社的ガバナンス・統一基準が推奨される。",
            "reference": "https://www.ipa.go.jp/ikc/reports/ai/ai-governance.html",
            "reference_label": "IPA AIガバナンス"
          }
        },
        {
          "key": "D",
          "text": "学習や推論での利用は著作権・プライバシーを考慮しなくてよい",
          "explanation": {
            "text": "権利・個人情報の配慮が必要で、社内ルールで管理すべきとされる。",
            "reference": "https://www.ipa.go.jp/ikc/reports/ai/ai-governance.html",
            "reference_label": "IPA AIガバナンス"
          }
        }
      ],
      "answer": "B",
      "explanation": {
        "text": "生成AIの実務利用では入力・出力・権利・個人情報・ログ等をルール化し、検証と説明可能性を確保することが肝要である。",
        "reference": "https://www.ipa.go.jp/ikc/reports/ai/ai-governance.html",
        "reference_label": "IPA AIガバナンス"
      }
    },
    {
      "id": "it-ST-q49",
      "question": "BCP/DR計画でRTO・RPOを定めた後、バックアップ／レプリケーション設計で優先的に確認すべき点はどれか。",
      "difficulty": "normal",
      "choices": [
        {
          "key": "A",
          "text": "バックアップ媒体の色や形状",
          "explanation": {
            "text": "物理的見た目ではなく復旧目標との整合が重要。",
            "reference": "https://www.ipa.go.jp/archive/digital/iot-en-ci/kousinrai/ent04-d.html",
            "reference_label": "IPA 高回復力システム基盤／RTO・RPOの整理"
          }
        },
        {
          "key": "B",
          "text": "取得間隔・保存先・復旧手順がRTO/RPOを満たすか（復元検証を含む）",
          "explanation": {
            "text": "RTO（許容停止時間）・RPO（許容データ損失）達成に直結する設計・検証が要となる。",
            "reference": "https://www.ipa.go.jp/archive/digital/iot-en-ci/kousinrai/ent04-d.html",
            "reference_label": "IPA 高回復力システム基盤／RTO・RPOの整理"
          }
        },
        {
          "key": "C",
          "text": "バックアップは取得すれば復元検証は不要",
          "explanation": {
            "text": "復元手順と検証がなければ実効性が担保できない。",
            "reference": "https://www.ipa.go.jp/archive/digital/iot-en-ci/kousinrai/ent04-d.html",
            "reference_label": "IPA 高回復力システム基盤／RTO・RPOの整理"
          }
        },
        {
          "key": "D",
          "text": "本番と同一拠点にのみ保存するのが最適",
          "explanation": {
            "text": "拠点障害に備えた遠隔保管や多重化が望ましい。",
            "reference": "https://www.ipa.go.jp/archive/digital/iot-en-ci/kousinrai/ent04-d.html",
            "reference_label": "IPA 高回復力システム基盤／RTO・RPOの整理"
          }
        }
      ],
      "answer": "B",
      "explanation": {
        "text": "RTO・RPOに合致する取得間隔・保存先・復旧手順、そして実機復元検証の有無が、実効性のあるBCP/DRの鍵となる。",
        "reference": "https://www.ipa.go.jp/archive/digital/iot-en-ci/kousinrai/ent04-d.html",
        "reference_label": "IPA 高回復力システム基盤／RTO・RPOの整理"
      }
    },
    {
      "id": "it-ST-q50",
      "question": "ISMS（情報セキュリティマネジメントシステム）におけるPDCA（Plan-Do-Check-Act）を継続的に回す主目的として最も適切なものはどれか。",
      "difficulty": "normal",
      "choices": [
        {
          "key": "A",
          "text": "一度策定したセキュリティ方針を固定し、運用を標準化するだけの仕組みにするため",
          "explanation": {
            "text": "ISMSは静的な標準化ではなく、環境変化やリスクの変動に応じた継続的改善を前提とする。",
            "reference": "https://www.ipa.go.jp/security/isec/jisq27001.html",
            "reference_label": "IPA ISMS関連解説（JIS Q 27001/27002の考え方）"
          }
        },
        {
          "key": "B",
          "text": "リスク評価とリスク対応の妥当性を定期的に見直し、セキュリティ目標と管理策を継続的に改善するため",
          "explanation": {
            "text": "ISMSのPDCAは、組織の状況や脅威の変化に合わせて目標・管理策・運用・監査・是正を回し、適合性・有効性を高めることが狙いである。",
            "reference": "https://www.ipa.go.jp/security/isec/jisq27001.html",
            "reference_label": "IPA ISMS関連解説（JIS Q 27001/27002の考え方）"
          }
        },
        {
          "key": "C",
          "text": "外部監査の指摘事項にのみ反応し、内部監査は省略するため",
          "explanation": {
            "text": "内部監査とマネジメントレビューはISMSの必須要素であり、省略は不適切である。",
            "reference": "https://www.ipa.go.jp/security/isec/jisq27001.html",
            "reference_label": "IPA ISMS関連解説（JIS Q 27001/27002の考え方）"
          }
        },
        {
          "key": "D",
          "text": "技術的管理策（アクセス制御や暗号化など）の導入だけで十分とし、組織的・人的管理は対象外にするため",
          "explanation": {
            "text": "ISMSは組織的・人的・物理的・技術的な統合管理を求め、特定層に偏らない包括的マネジメントを重視する。",
            "reference": "https://www.ipa.go.jp/security/isec/jisq27001.html",
            "reference_label": "IPA ISMS関連解説（JIS Q 27001/27002の考え方）"
          }
        }
      ],
      "answer": "B",
      "explanation": {
        "text": "ISMSは“リスクに基づくマネジメント”を核とし、PDCAにより環境・脅威・法令・事業要件の変化を取り込みながら、目標・管理策・運用・監査・是正を継続的に改善することで、有効性と適合性を高める。",
        "reference": "https://www.ipa.go.jp/security/isec/jisq27001.html",
        "reference_label": "IPA ISMS関連解説（JIS Q 27001/27002の考え方）"
      }
    }
  ]
}
